[
  {
    "date": "2025-01-02",
    "trade_date": "2025-01-02",
    "code": "601555",
    "open": 7.83,
    "close": 7.46,
    "high": 7.83,
    "low": 7.38,
    "volume": 71290711.0,
    "amount": null,
    "amplitude": null,
    "change_pct": null,
    "change": null,
    "turnover": null,
    "source": "sina.kline",
    "adjust": "raw"
  },
  {
    "date": "2025-01-03",
    "trade_date": "2025-01-03",
    "code": "601555",
    "open": 7.49,
    "close": 7.39,
    "high": 7.58,
    "low": 7.35,
    "volume": 51348536.0,
    "amount": null,
    "amplitude": null,
    "change_pct": null,
    "change": null,
    "turnover": null,
    "source": "sina.kline",
    "adjust": "raw"
  },
  {
    "date": "2025-01-06",
    "trade_date": "2025-01-06",
    "code": "601555",
    "open": 7.39,
    "close": 7.42,
    "high": 7.48,
    "low": 7.34,
    "volume": 35379150.0,
    "amount": null,
    "amplitude": null,
    "change_pct": null,
    "change": null,
    "turnover": null,
    "source": "sina.kline",
    "adjust": "raw"
  },
  {
    "date": "2025-01-07",
    "trade_date": "2025-01-07",
    "code": "601555",
    "open": 7.46,
    "close": 7.46,
    "high": 7.49,
    "low": 7.36,
    "volume": 36592733.0,
    "amount": null,
    "amplitude": null,
    "change_pct": null,
    "change": null,
    "turnover": null,
    "source": "sina.kline",
    "adjust": "raw"
  },
  {
    "date": "2025-01-08",
    "trade_date": "2025-01-08",
    "code": "601555",
    "open": 7.44,
    "close": 7.43,
    "high": 7.47,
    "low": 7.25,
    "volume": 48306406.0,
    "amount": null,
    "amplitude": null,
    "change_pct": null,
    "change": null,
    "turnover": null,
    "source": "sina.kline",
    "adjust": "raw"
  },
  {
    "date": "2025-01-09",
    "trade_date": "2025-01-09",
    "code": "601555",
    "open": 7.39,
    "close": 7.35,
    "high": 7.44,
    "low": 7.33,
    "volume": 25301964.0,
    "amount": null,
    "amplitude": null,
    "change_pct": null,
    "change": null,
    "turnover": null,
    "source": "sina.kline",
    "adjust": "raw"
  },
  {
    "date": "2025-01-10",
    "trade_date": "2025-01-10",
    "code": "601555",
    "open": 7.37,
    "close": 7.24,
    "high": 7.39,
    "low": 7.23,
    "volume": 27264546.0,
    "amount": null,
    "amplitude": null,
    "change_pct": null,
    "change": null,
    "turnover": null,
    "source": "sina.kline",
    "adjust": "raw"
  },
  {
    "date": "2025-01-13",
    "trade_date": "2025-01-13",
    "code": "601555",
    "open": 7.18,
    "close": 7.28,
    "high": 7.3,
    "low": 7.16,
    "volume": 28210063.0,
    "amount": null,
    "amplitude": null,
    "change_pct": null,
    "change": null,
    "turnover": null,
    "source": "sina.kline",
    "adjust": "raw"
  },
  {
    "date": "2025-01-14",
    "trade_date": "2025-01-14",
    "code": "601555",
    "open": 7.29,
    "close": 7.49,
    "high": 7.52,
    "low": 7.28,
    "volume": 54693438.0,
    "amount": null,
    "amplitude": null,
    "change_pct": null,
    "change": null,
    "turnover": null,
    "source": "sina.kline",
    "adjust": "raw"
  },
  {
    "date": "2025-01-15",
    "trade_date": "2025-01-15",
    "code": "601555",
    "open": 7.46,
    "close": 7.51,
    "high": 7.54,
    "low": 7.44,
    "volume": 45911084.0,
    "amount": null,
    "amplitude": null,
    "change_pct": null,
    "change": null,
    "turnover": null,
    "source": "sina.kline",
    "adjust": "raw"
  },
  {
    "date": "2025-01-16",
    "trade_date": "2025-01-16",
    "code": "601555",
    "open": 7.53,
    "close": 7.52,
    "high": 7.67,
    "low": 7.44,
    "volume": 40095362.0,
    "amount": null,
    "amplitude": null,
    "change_pct": null,
    "change": null,
    "turnover": null,
    "source": "sina.kline",
    "adjust": "raw"
  },
  {
    "date": "2025-01-17",
    "trade_date": "2025-01-17",
    "code": "601555",
    "open": 7.49,
    "close": 7.52,
    "high": 7.57,
    "low": 7.47,
    "volume": 29347058.0,
    "amount": null,
    "amplitude": null,
    "change_pct": null,
    "change": null,
    "turnover": null,
    "source": "sina.kline",
    "adjust": "raw"
  },
  {
    "date": "2025-01-20",
    "trade_date": "2025-01-20",
    "code": "601555",
    "open": 7.58,
    "close": 7.57,
    "high": 7.63,
    "low": 7.53,
    "volume": 31328795.0,
    "amount": null,
    "amplitude": null,
    "change_pct": null,
    "change": null,
    "turnover": null,
    "source": "sina.kline",
    "adjust": "raw"
  },
  {
    "date": "2025-01-21",
    "trade_date": "2025-01-21",
    "code": "601555",
    "open": 7.63,
    "close": 7.54,
    "high": 7.64,
    "low": 7.49,
    "volume": 28332282.0,
    "amount": null,
    "amplitude": null,
    "change_pct": null,
    "change": null,
    "turnover": null,
    "source": "sina.kline",
    "adjust": "raw"
  },
  {
    "date": "2025-01-22",
    "trade_date": "2025-01-22",
    "code": "601555",
    "open": 7.52,
    "close": 7.53,
    "high": 7.56,
    "low": 7.43,
    "volume": 27129059.0,
    "amount": null,
    "amplitude": null,
    "change_pct": null,
    "change": null,
    "turnover": null,
    "source": "sina.kline",
    "adjust": "raw"
  },
  {
    "date": "2025-01-23",
    "trade_date": "2025-01-23",
    "code": "601555",
    "open": 7.65,
    "close": 7.61,
    "high": 7.79,
    "low": 7.59,
    "volume": 52043906.0,
    "amount": null,
    "amplitude": null,
    "change_pct": null,
    "change": null,
    "turnover": null,
    "source": "sina.kline",
    "adjust": "raw"
  },
  {
    "date": "2025-01-24",
    "trade_date": "2025-01-24",
    "code": "601555",
    "open": 7.6,
    "close": 7.68,
    "high": 7.72,
    "low": 7.57,
    "volume": 42698526.0,
    "amount": null,
    "amplitude": null,
    "change_pct": null,
    "change": null,
    "turnover": null,
    "source": "sina.kline",
    "adjust": "raw"
  },
  {
    "date": "2025-01-27",
    "trade_date": "2025-01-27",
    "code": "601555",
    "open": 7.71,
    "close": 7.5,
    "high": 7.73,
    "low": 7.5,
    "volume": 34632530.0,
    "amount": null,
    "amplitude": null,
    "change_pct": null,
    "change": null,
    "turnover": null,
    "source": "sina.kline",
    "adjust": "raw"
  },
  {
    "date": "2025-02-05",
    "trade_date": "2025-02-05",
    "code": "601555",
    "open": 7.55,
    "close": 7.5,
    "high": 7.6,
    "low": 7.47,
    "volume": 30881786.0,
    "amount": null,
    "amplitude": null,
    "change_pct": null,
    "change": null,
    "turnover": null,
    "source": "sina.kline",
    "adjust": "raw"
  },
  {
    "date": "2025-02-06",
    "trade_date": "2025-02-06",
    "code": "601555",
    "open": 7.48,
    "close": 7.58,
    "high": 7.61,
    "low": 7.45,
    "volume": 37627529.0,
    "amount": null,
    "amplitude": null,
    "change_pct": null,
    "change": null,
    "turnover": null,
    "source": "sina.kline",
    "adjust": "raw"
  },
  {
    "date": "2025-02-07",
    "trade_date": "2025-02-07",
    "code": "601555",
    "open": 7.59,
    "close": 7.75,
    "high": 7.84,
    "low": 7.56,
    "volume": 64168006.0,
    "amount": null,
    "amplitude": null,
    "change_pct": null,
    "change": null,
    "turnover": null,
    "source": "sina.kline",
    "adjust": "raw"
  },
  {
    "date": "2025-02-10",
    "trade_date": "2025-02-10",
    "code": "601555",
    "open": 7.74,
    "close": 7.76,
    "high": 7.84,
    "low": 7.72,
    "volume": 35983963.0,
    "amount": null,
    "amplitude": null,
    "change_pct": null,
    "change": null,
    "turnover": null,
    "source": "sina.kline",
    "adjust": "raw"
  },
  {
    "date": "2025-02-11",
    "trade_date": "2025-02-11",
    "code": "601555",
    "open": 7.77,
    "close": 7.78,
    "high": 7.81,
    "low": 7.66,
    "volume": 43374576.0,
    "amount": null,
    "amplitude": null,
    "change_pct": null,
    "change": null,
    "turnover": null,
    "source": "sina.kline",
    "adjust": "raw"
  },
  {
    "date": "2025-02-12",
    "trade_date": "2025-02-12",
    "code": "601555",
    "open": 7.75,
    "close": 7.89,
    "high": 7.89,
    "low": 7.74,
    "volume": 56706497.0,
    "amount": null,
    "amplitude": null,
    "change_pct": null,
    "change": null,
    "turnover": null,
    "source": "sina.kline",
    "adjust": "raw"
  },
  {
    "date": "2025-02-13",
    "trade_date": "2025-02-13",
    "code": "601555",
    "open": 7.88,
    "close": 7.88,
    "high": 7.97,
    "low": 7.8,
    "volume": 60579172.0,
    "amount": null,
    "amplitude": null,
    "change_pct": null,
    "change": null,
    "turnover": null,
    "source": "sina.kline",
    "adjust": "raw"
  },
  {
    "date": "2025-02-14",
    "trade_date": "2025-02-14",
    "code": "601555",
    "open": 7.86,
    "close": 7.88,
    "high": 7.92,
    "low": 7.81,
    "volume": 35805687.0,
    "amount": null,
    "amplitude": null,
    "change_pct": null,
    "change": null,
    "turnover": null,
    "source": "sina.kline",
    "adjust": "raw"
  },
  {
    "date": "2025-02-17",
    "trade_date": "2025-02-17",
    "code": "601555",
    "open": 7.94,
    "close": 7.88,
    "high": 7.97,
    "low": 7.83,
    "volume": 42786977.0,
    "amount": null,
    "amplitude": null,
    "change_pct": null,
    "change": null,
    "turnover": null,
    "source": "sina.kline",
    "adjust": "raw"
  },
  {
    "date": "2025-02-18",
    "trade_date": "2025-02-18",
    "code": "601555",
    "open": 7.86,
    "close": 7.75,
    "high": 7.89,
    "low": 7.71,
    "volume": 44957211.0,
    "amount": null,
    "amplitude": null,
    "change_pct": null,
    "change": null,
    "turnover": null,
    "source": "sina.kline",
    "adjust": "raw"
  },
  {
    "date": "2025-02-19",
    "trade_date": "2025-02-19",
    "code": "601555",
    "open": 7.74,
    "close": 7.82,
    "high": 7.87,
    "low": 7.73,
    "volume": 39710774.0,
    "amount": null,
    "amplitude": null,
    "change_pct": null,
    "change": null,
    "turnover": null,
    "source": "sina.kline",
    "adjust": "raw"
  },
  {
    "date": "2025-02-20",
    "trade_date": "2025-02-20",
    "code": "601555",
    "open": 7.79,
    "close": 7.8,
    "high": 7.85,
    "low": 7.74,
    "volume": 35059832.0,
    "amount": null,
    "amplitude": null,
    "change_pct": null,
    "change": null,
    "turnover": null,
    "source": "sina.kline",
    "adjust": "raw"
  },
  {
    "date": "2025-02-21",
    "trade_date": "2025-02-21",
    "code": "601555",
    "open": 7.82,
    "close": 8.15,
    "high": 8.19,
    "low": 7.81,
    "volume": 122863144.0,
    "amount": null,
    "amplitude": null,
    "change_pct": null,
    "change": null,
    "turnover": null,
    "source": "sina.kline",
    "adjust": "raw"
  },
  {
    "date": "2025-02-24",
    "trade_date": "2025-02-24",
    "code": "601555",
    "open": 8.1,
    "close": 7.98,
    "high": 8.11,
    "low": 7.95,
    "volume": 77239724.0,
    "amount": null,
    "amplitude": null,
    "change_pct": null,
    "change": null,
    "turnover": null,
    "source": "sina.kline",
    "adjust": "raw"
  },
  {
    "date": "2025-02-25",
    "trade_date": "2025-02-25",
    "code": "601555",
    "open": 7.91,
    "close": 7.97,
    "high": 8.02,
    "low": 7.9,
    "volume": 43086559.0,
    "amount": null,
    "amplitude": null,
    "change_pct": null,
    "change": null,
    "turnover": null,
    "source": "sina.kline",
    "adjust": "raw"
  },
  {
    "date": "2025-02-26",
    "trade_date": "2025-02-26",
    "code": "601555",
    "open": 7.96,
    "close": 8.1,
    "high": 8.11,
    "low": 7.96,
    "volume": 53031204.0,
    "amount": null,
    "amplitude": null,
    "change_pct": null,
    "change": null,
    "turnover": null,
    "source": "sina.kline",
    "adjust": "raw"
  },
  {
    "date": "2025-02-27",
    "trade_date": "2025-02-27",
    "code": "601555",
    "open": 8.06,
    "close": 8.08,
    "high": 8.12,
    "low": 7.95,
    "volume": 57837542.0,
    "amount": null,
    "amplitude": null,
    "change_pct": null,
    "change": null,
    "turnover": null,
    "source": "sina.kline",
    "adjust": "raw"
  },
  {
    "date": "2025-02-28",
    "trade_date": "2025-02-28",
    "code": "601555",
    "open": 8.05,
    "close": 7.99,
    "high": 8.14,
    "low": 7.92,
    "volume": 61678613.0,
    "amount": null,
    "amplitude": null,
    "change_pct": null,
    "change": null,
    "turnover": null,
    "source": "sina.kline",
    "adjust": "raw"
  },
  {
    "date": "2025-03-03",
    "trade_date": "2025-03-03",
    "code": "601555",
    "open": 7.97,
    "close": 7.93,
    "high": 7.99,
    "low": 7.87,
    "volume": 48722052.0,
    "amount": null,
    "amplitude": null,
    "change_pct": null,
    "change": null,
    "turnover": null,
    "source": "sina.kline",
    "adjust": "raw"
  },
  {
    "date": "2025-03-04",
    "trade_date": "2025-03-04",
    "code": "601555",
    "open": 7.88,
    "close": 7.95,
    "high": 8.01,
    "low": 7.87,
    "volume": 28756574.0,
    "amount": null,
    "amplitude": null,
    "change_pct": null,
    "change": null,
    "turnover": null,
    "source": "sina.kline",
    "adjust": "raw"
  },
  {
    "date": "2025-03-05",
    "trade_date": "2025-03-05",
    "code": "601555",
    "open": 7.93,
    "close": 8.02,
    "high": 8.07,
    "low": 7.88,
    "volume": 41308572.0,
    "amount": null,
    "amplitude": null,
    "change_pct": null,
    "change": null,
    "turnover": null,
    "source": "sina.kline",
    "adjust": "raw"
  },
  {
    "date": "2025-03-06",
    "trade_date": "2025-03-06",
    "code": "601555",
    "open": 8.07,
    "close": 8.13,
    "high": 8.17,
    "low": 8.01,
    "volume": 62633010.0,
    "amount": null,
    "amplitude": null,
    "change_pct": null,
    "change": null,
    "turnover": null,
    "source": "sina.kline",
    "adjust": "raw"
  },
  {
    "date": "2025-03-07",
    "trade_date": "2025-03-07",
    "code": "601555",
    "open": 8.08,
    "close": 8.05,
    "high": 8.11,
    "low": 8.02,
    "volume": 35590878.0,
    "amount": null,
    "amplitude": null,
    "change_pct": null,
    "change": null,
    "turnover": null,
    "source": "sina.kline",
    "adjust": "raw"
  },
  {
    "date": "2025-03-10",
    "trade_date": "2025-03-10",
    "code": "601555",
    "open": 8.04,
    "close": 7.99,
    "high": 8.05,
    "low": 7.95,
    "volume": 25739224.0,
    "amount": null,
    "amplitude": null,
    "change_pct": null,
    "change": null,
    "turnover": null,
    "source": "sina.kline",
    "adjust": "raw"
  },
  {
    "date": "2025-03-11",
    "trade_date": "2025-03-11",
    "code": "601555",
    "open": 7.92,
    "close": 8.02,
    "high": 8.03,
    "low": 7.91,
    "volume": 28102609.0,
    "amount": null,
    "amplitude": null,
    "change_pct": null,
    "change": null,
    "turnover": null,
    "source": "sina.kline",
    "adjust": "raw"
  },
  {
    "date": "2025-03-12",
    "trade_date": "2025-03-12",
    "code": "601555",
    "open": 8.03,
    "close": 8.09,
    "high": 8.14,
    "low": 8.0,
    "volume": 36860081.0,
    "amount": null,
    "amplitude": null,
    "change_pct": null,
    "change": null,
    "turnover": null,
    "source": "sina.kline",
    "adjust": "raw"
  },
  {
    "date": "2025-03-13",
    "trade_date": "2025-03-13",
    "code": "601555",
    "open": 8.06,
    "close": 8.0,
    "high": 8.13,
    "low": 7.96,
    "volume": 35221532.0,
    "amount": null,
    "amplitude": null,
    "change_pct": null,
    "change": null,
    "turnover": null,
    "source": "sina.kline",
    "adjust": "raw"
  },
  {
    "date": "2025-03-14",
    "trade_date": "2025-03-14",
    "code": "601555",
    "open": 8.02,
    "close": 8.21,
    "high": 8.28,
    "low": 8.02,
    "volume": 86284096.0,
    "amount": null,
    "amplitude": null,
    "change_pct": null,
    "change": null,
    "turnover": null,
    "source": "sina.kline",
    "adjust": "raw"
  },
  {
    "date": "2025-03-17",
    "trade_date": "2025-03-17",
    "code": "601555",
    "open": 8.25,
    "close": 8.12,
    "high": 8.25,
    "low": 8.11,
    "volume": 39329561.0,
    "amount": null,
    "amplitude": null,
    "change_pct": null,
    "change": null,
    "turnover": null,
    "source": "sina.kline",
    "adjust": "raw"
  },
  {
    "date": "2025-03-18",
    "trade_date": "2025-03-18",
    "code": "601555",
    "open": 8.17,
    "close": 8.12,
    "high": 8.18,
    "low": 8.1,
    "volume": 27907589.0,
    "amount": null,
    "amplitude": null,
    "change_pct": null,
    "change": null,
    "turnover": null,
    "source": "sina.kline",
    "adjust": "raw"
  },
  {
    "date": "2025-03-19",
    "trade_date": "2025-03-19",
    "code": "601555",
    "open": 8.13,
    "close": 8.15,
    "high": 8.19,
    "low": 8.1,
    "volume": 32611685.0,
    "amount": null,
    "amplitude": null,
    "change_pct": null,
    "change": null,
    "turnover": null,
    "source": "sina.kline",
    "adjust": "raw"
  },
  {
    "date": "2025-03-20",
    "trade_date": "2025-03-20",
    "code": "601555",
    "open": 8.14,
    "close": 8.06,
    "high": 8.15,
    "low": 8.05,
    "volume": 31686158.0,
    "amount": null,
    "amplitude": null,
    "change_pct": null,
    "change": null,
    "turnover": null,
    "source": "sina.kline",
    "adjust": "raw"
  },
  {
    "date": "2025-03-21",
    "trade_date": "2025-03-21",
    "code": "601555",
    "open": 8.05,
    "close": 7.98,
    "high": 8.09,
    "low": 7.91,
    "volume": 37450161.0,
    "amount": null,
    "amplitude": null,
    "change_pct": null,
    "change": null,
    "turnover": null,
    "source": "sina.kline",
    "adjust": "raw"
  },
  {
    "date": "2025-03-24",
    "trade_date": "2025-03-24",
    "code": "601555",
    "open": 7.94,
    "close": 7.96,
    "high": 7.98,
    "low": 7.88,
    "volume": 25469571.0,
    "amount": null,
    "amplitude": null,
    "change_pct": null,
    "change": null,
    "turnover": null,
    "source": "sina.kline",
    "adjust": "raw"
  },
  {
    "date": "2025-03-25",
    "trade_date": "2025-03-25",
    "code": "601555",
    "open": 7.97,
    "close": 7.95,
    "high": 8.0,
    "low": 7.91,
    "volume": 19876217.0,
    "amount": null,
    "amplitude": null,
    "change_pct": null,
    "change": null,
    "turnover": null,
    "source": "sina.kline",
    "adjust": "raw"
  },
  {
    "date": "2025-03-26",
    "trade_date": "2025-03-26",
    "code": "601555",
    "open": 7.92,
    "close": 7.92,
    "high": 7.96,
    "low": 7.91,
    "volume": 19308275.0,
    "amount": null,
    "amplitude": null,
    "change_pct": null,
    "change": null,
    "turnover": null,
    "source": "sina.kline",
    "adjust": "raw"
  },
  {
    "date": "2025-03-27",
    "trade_date": "2025-03-27",
    "code": "601555",
    "open": 7.91,
    "close": 7.93,
    "high": 7.97,
    "low": 7.87,
    "volume": 23536781.0,
    "amount": null,
    "amplitude": null,
    "change_pct": null,
    "change": null,
    "turnover": null,
    "source": "sina.kline",
    "adjust": "raw"
  },
  {
    "date": "2025-03-28",
    "trade_date": "2025-03-28",
    "code": "601555",
    "open": 7.92,
    "close": 7.91,
    "high": 7.96,
    "low": 7.89,
    "volume": 19933743.0,
    "amount": null,
    "amplitude": null,
    "change_pct": null,
    "change": null,
    "turnover": null,
    "source": "sina.kline",
    "adjust": "raw"
  },
  {
    "date": "2025-03-31",
    "trade_date": "2025-03-31",
    "code": "601555",
    "open": 7.9,
    "close": 7.8,
    "high": 7.93,
    "low": 7.74,
    "volume": 28369916.0,
    "amount": null,
    "amplitude": null,
    "change_pct": null,
    "change": null,
    "turnover": null,
    "source": "sina.kline",
    "adjust": "raw"
  },
  {
    "date": "2025-04-01",
    "trade_date": "2025-04-01",
    "code": "601555",
    "open": 7.8,
    "close": 7.77,
    "high": 7.86,
    "low": 7.76,
    "volume": 26488190.0,
    "amount": null,
    "amplitude": null,
    "change_pct": null,
    "change": null,
    "turnover": null,
    "source": "sina.kline",
    "adjust": "raw"
  },
  {
    "date": "2025-04-02",
    "trade_date": "2025-04-02",
    "code": "601555",
    "open": 7.78,
    "close": 7.86,
    "high": 7.86,
    "low": 7.76,
    "volume": 20629622.0,
    "amount": null,
    "amplitude": null,
    "change_pct": null,
    "change": null,
    "turnover": null,
    "source": "sina.kline",
    "adjust": "raw"
  },
  {
    "date": "2025-04-03",
    "trade_date": "2025-04-03",
    "code": "601555",
    "open": 7.81,
    "close": 7.79,
    "high": 7.88,
    "low": 7.77,
    "volume": 28199210.0,
    "amount": null,
    "amplitude": null,
    "change_pct": null,
    "change": null,
    "turnover": null,
    "source": "sina.kline",
    "adjust": "raw"
  },
  {
    "date": "2025-04-07",
    "trade_date": "2025-04-07",
    "code": "601555",
    "open": 7.47,
    "close": 7.05,
    "high": 7.54,
    "low": 7.01,
    "volume": 102473203.0,
    "amount": null,
    "amplitude": null,
    "change_pct": null,
    "change": null,
    "turnover": null,
    "source": "sina.kline",
    "adjust": "raw"
  },
  {
    "date": "2025-04-08",
    "trade_date": "2025-04-08",
    "code": "601555",
    "open": 7.07,
    "close": 7.16,
    "high": 7.18,
    "low": 7.04,
    "volume": 52824237.0,
    "amount": null,
    "amplitude": null,
    "change_pct": null,
    "change": null,
    "turnover": null,
    "source": "sina.kline",
    "adjust": "raw"
  },
  {
    "date": "2025-04-09",
    "trade_date": "2025-04-09",
    "code": "601555",
    "open": 7.35,
    "close": 7.62,
    "high": 7.88,
    "low": 7.27,
    "volume": 151634011.0,
    "amount": null,
    "amplitude": null,
    "change_pct": null,
    "change": null,
    "turnover": null,
    "source": "sina.kline",
    "adjust": "raw"
  },
  {
    "date": "2025-04-10",
    "trade_date": "2025-04-10",
    "code": "601555",
    "open": 7.59,
    "close": 7.58,
    "high": 7.68,
    "low": 7.5,
    "volume": 111080535.0,
    "amount": null,
    "amplitude": null,
    "change_pct": null,
    "change": null,
    "turnover": null,
    "source": "sina.kline",
    "adjust": "raw"
  },
  {
    "date": "2025-04-11",
    "trade_date": "2025-04-11",
    "code": "601555",
    "open": 7.61,
    "close": 7.5,
    "high": 7.65,
    "low": 7.48,
    "volume": 58665058.0,
    "amount": null,
    "amplitude": null,
    "change_pct": null,
    "change": null,
    "turnover": null,
    "source": "sina.kline",
    "adjust": "raw"
  },
  {
    "date": "2025-04-14",
    "trade_date": "2025-04-14",
    "code": "601555",
    "open": 7.56,
    "close": 7.53,
    "high": 7.57,
    "low": 7.49,
    "volume": 43196277.0,
    "amount": null,
    "amplitude": null,
    "change_pct": null,
    "change": null,
    "turnover": null,
    "source": "sina.kline",
    "adjust": "raw"
  },
  {
    "date": "2025-04-15",
    "trade_date": "2025-04-15",
    "code": "601555",
    "open": 7.54,
    "close": 7.51,
    "high": 7.54,
    "low": 7.47,
    "volume": 25983815.0,
    "amount": null,
    "amplitude": null,
    "change_pct": null,
    "change": null,
    "turnover": null,
    "source": "sina.kline",
    "adjust": "raw"
  },
  {
    "date": "2025-04-16",
    "trade_date": "2025-04-16",
    "code": "601555",
    "open": 7.51,
    "close": 7.59,
    "high": 7.59,
    "low": 7.45,
    "volume": 41285575.0,
    "amount": null,
    "amplitude": null,
    "change_pct": null,
    "change": null,
    "turnover": null,
    "source": "sina.kline",
    "adjust": "raw"
  },
  {
    "date": "2025-04-17",
    "trade_date": "2025-04-17",
    "code": "601555",
    "open": 7.56,
    "close": 7.57,
    "high": 7.59,
    "low": 7.51,
    "volume": 30815579.0,
    "amount": null,
    "amplitude": null,
    "change_pct": null,
    "change": null,
    "turnover": null,
    "source": "sina.kline",
    "adjust": "raw"
  },
  {
    "date": "2025-04-18",
    "trade_date": "2025-04-18",
    "code": "601555",
    "open": 7.54,
    "close": 7.6,
    "high": 7.62,
    "low": 7.52,
    "volume": 30890456.0,
    "amount": null,
    "amplitude": null,
    "change_pct": null,
    "change": null,
    "turnover": null,
    "source": "sina.kline",
    "adjust": "raw"
  },
  {
    "date": "2025-04-21",
    "trade_date": "2025-04-21",
    "code": "601555",
    "open": 7.59,
    "close": 7.64,
    "high": 7.65,
    "low": 7.56,
    "volume": 31529650.0,
    "amount": null,
    "amplitude": null,
    "change_pct": null,
    "change": null,
    "turnover": null,
    "source": "sina.kline",
    "adjust": "raw"
  },
  {
    "date": "2025-04-22",
    "trade_date": "2025-04-22",
    "code": "601555",
    "open": 7.62,
    "close": 7.63,
    "high": 7.68,
    "low": 7.61,
    "volume": 34901325.0,
    "amount": null,
    "amplitude": null,
    "change_pct": null,
    "change": null,
    "turnover": null,
    "source": "sina.kline",
    "adjust": "raw"
  },
  {
    "date": "2025-04-23",
    "trade_date": "2025-04-23",
    "code": "601555",
    "open": 7.65,
    "close": 7.63,
    "high": 7.69,
    "low": 7.61,
    "volume": 32140395.0,
    "amount": null,
    "amplitude": null,
    "change_pct": null,
    "change": null,
    "turnover": null,
    "source": "sina.kline",
    "adjust": "raw"
  },
  {
    "date": "2025-04-24",
    "trade_date": "2025-04-24",
    "code": "601555",
    "open": 7.64,
    "close": 7.68,
    "high": 7.82,
    "low": 7.62,
    "volume": 52856244.0,
    "amount": null,
    "amplitude": null,
    "change_pct": null,
    "change": null,
    "turnover": null,
    "source": "sina.kline",
    "adjust": "raw"
  },
  {
    "date": "2025-04-25",
    "trade_date": "2025-04-25",
    "code": "601555",
    "open": 7.71,
    "close": 7.8,
    "high": 7.82,
    "low": 7.67,
    "volume": 44152184.0,
    "amount": null,
    "amplitude": null,
    "change_pct": null,
    "change": null,
    "turnover": null,
    "source": "sina.kline",
    "adjust": "raw"
  },
  {
    "date": "2025-04-28",
    "trade_date": "2025-04-28",
    "code": "601555",
    "open": 7.91,
    "close": 7.89,
    "high": 8.01,
    "low": 7.84,
    "volume": 74576284.0,
    "amount": null,
    "amplitude": null,
    "change_pct": null,
    "change": null,
    "turnover": null,
    "source": "sina.kline",
    "adjust": "raw"
  },
  {
    "date": "2025-04-29",
    "trade_date": "2025-04-29",
    "code": "601555",
    "open": 7.86,
    "close": 7.85,
    "high": 7.99,
    "low": 7.84,
    "volume": 52242439.0,
    "amount": null,
    "amplitude": null,
    "change_pct": null,
    "change": null,
    "turnover": null,
    "source": "sina.kline",
    "adjust": "raw"
  },
  {
    "date": "2025-04-30",
    "trade_date": "2025-04-30",
    "code": "601555",
    "open": 7.86,
    "close": 7.83,
    "high": 7.93,
    "low": 7.8,
    "volume": 45558190.0,
    "amount": null,
    "amplitude": null,
    "change_pct": null,
    "change": null,
    "turnover": null,
    "source": "sina.kline",
    "adjust": "raw"
  },
  {
    "date": "2025-05-06",
    "trade_date": "2025-05-06",
    "code": "601555",
    "open": 7.85,
    "close": 7.92,
    "high": 7.94,
    "low": 7.83,
    "volume": 65495515.0,
    "amount": null,
    "amplitude": null,
    "change_pct": null,
    "change": null,
    "turnover": null,
    "source": "sina.kline",
    "adjust": "raw"
  },
  {
    "date": "2025-05-07",
    "trade_date": "2025-05-07",
    "code": "601555",
    "open": 8.09,
    "close": 7.95,
    "high": 8.12,
    "low": 7.89,
    "volume": 69072490.0,
    "amount": null,
    "amplitude": null,
    "change_pct": null,
    "change": null,
    "turnover": null,
    "source": "sina.kline",
    "adjust": "raw"
  },
  {
    "date": "2025-05-08",
    "trade_date": "2025-05-08",
    "code": "601555",
    "open": 7.92,
    "close": 7.93,
    "high": 7.96,
    "low": 7.87,
    "volume": 36089467.0,
    "amount": null,
    "amplitude": null,
    "change_pct": null,
    "change": null,
    "turnover": null,
    "source": "sina.kline",
    "adjust": "raw"
  },
  {
    "date": "2025-05-09",
    "trade_date": "2025-05-09",
    "code": "601555",
    "open": 7.94,
    "close": 7.89,
    "high": 7.94,
    "low": 7.86,
    "volume": 28394439.0,
    "amount": null,
    "amplitude": null,
    "change_pct": null,
    "change": null,
    "turnover": null,
    "source": "sina.kline",
    "adjust": "raw"
  },
  {
    "date": "2025-05-12",
    "trade_date": "2025-05-12",
    "code": "601555",
    "open": 7.93,
    "close": 7.96,
    "high": 7.98,
    "low": 7.89,
    "volume": 58825333.0,
    "amount": null,
    "amplitude": null,
    "change_pct": null,
    "change": null,
    "turnover": null,
    "source": "sina.kline",
    "adjust": "raw"
  },
  {
    "date": "2025-05-13",
    "trade_date": "2025-05-13",
    "code": "601555",
    "open": 8.01,
    "close": 7.95,
    "high": 8.01,
    "low": 7.89,
    "volume": 50006430.0,
    "amount": null,
    "amplitude": null,
    "change_pct": null,
    "change": null,
    "turnover": null,
    "source": "sina.kline",
    "adjust": "raw"
  },
  {
    "date": "2025-05-14",
    "trade_date": "2025-05-14",
    "code": "601555",
    "open": 7.94,
    "close": 8.2,
    "high": 8.28,
    "low": 7.89,
    "volume": 121037214.0,
    "amount": null,
    "amplitude": null,
    "change_pct": null,
    "change": null,
    "turnover": null,
    "source": "sina.kline",
    "adjust": "raw"
  },
  {
    "date": "2025-05-15",
    "trade_date": "2025-05-15",
    "code": "601555",
    "open": 8.13,
    "close": 8.05,
    "high": 8.18,
    "low": 8.05,
    "volume": 55551199.0,
    "amount": null,
    "amplitude": null,
    "change_pct": null,
    "change": null,
    "turnover": null,
    "source": "sina.kline",
    "adjust": "raw"
  },
  {
    "date": "2025-05-16",
    "trade_date": "2025-05-16",
    "code": "601555",
    "open": 8.05,
    "close": 7.98,
    "high": 8.08,
    "low": 7.94,
    "volume": 43944615.0,
    "amount": null,
    "amplitude": null,
    "change_pct": null,
    "change": null,
    "turnover": null,
    "source": "sina.kline",
    "adjust": "raw"
  },
  {
    "date": "2025-05-19",
    "trade_date": "2025-05-19",
    "code": "601555",
    "open": 7.97,
    "close": 7.97,
    "high": 8.0,
    "low": 7.93,
    "volume": 28129266.0,
    "amount": null,
    "amplitude": null,
    "change_pct": null,
    "change": null,
    "turnover": null,
    "source": "sina.kline",
    "adjust": "raw"
  },
  {
    "date": "2025-05-20",
    "trade_date": "2025-05-20",
    "code": "601555",
    "open": 7.97,
    "close": 7.99,
    "high": 8.02,
    "low": 7.94,
    "volume": 31020922.0,
    "amount": null,
    "amplitude": null,
    "change_pct": null,
    "change": null,
    "turnover": null,
    "source": "sina.kline",
    "adjust": "raw"
  },
  {
    "date": "2025-05-21",
    "trade_date": "2025-05-21",
    "code": "601555",
    "open": 7.97,
    "close": 7.99,
    "high": 8.02,
    "low": 7.96,
    "volume": 27776304.0,
    "amount": null,
    "amplitude": null,
    "change_pct": null,
    "change": null,
    "turnover": null,
    "source": "sina.kline",
    "adjust": "raw"
  },
  {
    "date": "2025-05-22",
    "trade_date": "2025-05-22",
    "code": "601555",
    "open": 7.97,
    "close": 7.95,
    "high": 7.99,
    "low": 7.91,
    "volume": 24320323.0,
    "amount": null,
    "amplitude": null,
    "change_pct": null,
    "change": null,
    "turnover": null,
    "source": "sina.kline",
    "adjust": "raw"
  },
  {
    "date": "2025-05-23",
    "trade_date": "2025-05-23",
    "code": "601555",
    "open": 7.94,
    "close": 7.88,
    "high": 8.0,
    "low": 7.87,
    "volume": 37470823.0,
    "amount": null,
    "amplitude": null,
    "change_pct": null,
    "change": null,
    "turnover": null,
    "source": "sina.kline",
    "adjust": "raw"
  },
  {
    "date": "2025-05-26",
    "trade_date": "2025-05-26",
    "code": "601555",
    "open": 7.85,
    "close": 7.85,
    "high": 7.88,
    "low": 7.81,
    "volume": 24076824.0,
    "amount": null,
    "amplitude": null,
    "change_pct": null,
    "change": null,
    "turnover": null,
    "source": "sina.kline",
    "adjust": "raw"
  },
  {
    "date": "2025-05-27",
    "trade_date": "2025-05-27",
    "code": "601555",
    "open": 7.84,
    "close": 7.89,
    "high": 7.91,
    "low": 7.81,
    "volume": 23309684.0,
    "amount": null,
    "amplitude": null,
    "change_pct": null,
    "change": null,
    "turnover": null,
    "source": "sina.kline",
    "adjust": "raw"
  },
  {
    "date": "2025-05-28",
    "trade_date": "2025-05-28",
    "code": "601555",
    "open": 7.9,
    "close": 7.89,
    "high": 7.92,
    "low": 7.85,
    "volume": 17205094.0,
    "amount": null,
    "amplitude": null,
    "change_pct": null,
    "change": null,
    "turnover": null,
    "source": "sina.kline",
    "adjust": "raw"
  },
  {
    "date": "2025-05-29",
    "trade_date": "2025-05-29",
    "code": "601555",
    "open": 7.88,
    "close": 7.95,
    "high": 7.98,
    "low": 7.87,
    "volume": 28773911.0,
    "amount": null,
    "amplitude": null,
    "change_pct": null,
    "change": null,
    "turnover": null,
    "source": "sina.kline",
    "adjust": "raw"
  },
  {
    "date": "2025-05-30",
    "trade_date": "2025-05-30",
    "code": "601555",
    "open": 7.93,
    "close": 7.97,
    "high": 7.98,
    "low": 7.88,
    "volume": 31555370.0,
    "amount": null,
    "amplitude": null,
    "change_pct": null,
    "change": null,
    "turnover": null,
    "source": "sina.kline",
    "adjust": "raw"
  },
  {
    "date": "2025-06-03",
    "trade_date": "2025-06-03",
    "code": "601555",
    "open": 7.93,
    "close": 8.01,
    "high": 8.04,
    "low": 7.91,
    "volume": 34218180.0,
    "amount": null,
    "amplitude": null,
    "change_pct": null,
    "change": null,
    "turnover": null,
    "source": "sina.kline",
    "adjust": "raw"
  },
  {
    "date": "2025-06-04",
    "trade_date": "2025-06-04",
    "code": "601555",
    "open": 8.02,
    "close": 8.2,
    "high": 8.2,
    "low": 8.0,
    "volume": 59397289.0,
    "amount": null,
    "amplitude": null,
    "change_pct": null,
    "change": null,
    "turnover": null,
    "source": "sina.kline",
    "adjust": "raw"
  },
  {
    "date": "2025-06-05",
    "trade_date": "2025-06-05",
    "code": "601555",
    "open": 8.18,
    "close": 8.41,
    "high": 8.49,
    "low": 8.17,
    "volume": 101640674.0,
    "amount": null,
    "amplitude": null,
    "change_pct": null,
    "change": null,
    "turnover": null,
    "source": "sina.kline",
    "adjust": "raw"
  },
  {
    "date": "2025-06-06",
    "trade_date": "2025-06-06",
    "code": "601555",
    "open": 8.4,
    "close": 8.38,
    "high": 8.56,
    "low": 8.35,
    "volume": 81039680.0,
    "amount": null,
    "amplitude": null,
    "change_pct": null,
    "change": null,
    "turnover": null,
    "source": "sina.kline",
    "adjust": "raw"
  },
  {
    "date": "2025-06-09",
    "trade_date": "2025-06-09",
    "code": "601555",
    "open": 8.45,
    "close": 8.4,
    "high": 8.49,
    "low": 8.36,
    "volume": 53426835.0,
    "amount": null,
    "amplitude": null,
    "change_pct": null,
    "change": null,
    "turnover": null,
    "source": "sina.kline",
    "adjust": "raw"
  },
  {
    "date": "2025-06-10",
    "trade_date": "2025-06-10",
    "code": "601555",
    "open": 8.37,
    "close": 8.35,
    "high": 8.55,
    "low": 8.29,
    "volume": 65900877.0,
    "amount": null,
    "amplitude": null,
    "change_pct": null,
    "change": null,
    "turnover": null,
    "source": "sina.kline",
    "adjust": "raw"
  },
  {
    "date": "2025-06-11",
    "trade_date": "2025-06-11",
    "code": "601555",
    "open": 8.15,
    "close": 8.3,
    "high": 8.42,
    "low": 8.15,
    "volume": 81752704.0,
    "amount": null,
    "amplitude": null,
    "change_pct": null,
    "change": null,
    "turnover": null,
    "source": "sina.kline",
    "adjust": "raw"
  },
  {
    "date": "2025-06-12",
    "trade_date": "2025-06-12",
    "code": "601555",
    "open": 8.24,
    "close": 8.26,
    "high": 8.35,
    "low": 8.22,
    "volume": 56695336.0,
    "amount": null,
    "amplitude": null,
    "change_pct": null,
    "change": null,
    "turnover": null,
    "source": "sina.kline",
    "adjust": "raw"
  },
  {
    "date": "2025-06-13",
    "trade_date": "2025-06-13",
    "code": "601555",
    "open": 8.26,
    "close": 8.38,
    "high": 8.41,
    "low": 8.22,
    "volume": 91581217.0,
    "amount": null,
    "amplitude": null,
    "change_pct": null,
    "change": null,
    "turnover": null,
    "source": "sina.kline",
    "adjust": "raw"
  },
  {
    "date": "2025-06-16",
    "trade_date": "2025-06-16",
    "code": "601555",
    "open": 8.32,
    "close": 8.76,
    "high": 8.81,
    "low": 8.32,
    "volume": 122685161.0,
    "amount": null,
    "amplitude": null,
    "change_pct": null,
    "change": null,
    "turnover": null,
    "source": "sina.kline",
    "adjust": "raw"
  },
  {
    "date": "2025-06-17",
    "trade_date": "2025-06-17",
    "code": "601555",
    "open": 8.7,
    "close": 8.74,
    "high": 8.85,
    "low": 8.66,
    "volume": 84396779.0,
    "amount": null,
    "amplitude": null,
    "change_pct": null,
    "change": null,
    "turnover": null,
    "source": "sina.kline",
    "adjust": "raw"
  },
  {
    "date": "2025-06-18",
    "trade_date": "2025-06-18",
    "code": "601555",
    "open": 8.76,
    "close": 8.52,
    "high": 8.81,
    "low": 8.42,
    "volume": 75625144.0,
    "amount": null,
    "amplitude": null,
    "change_pct": null,
    "change": null,
    "turnover": null,
    "source": "sina.kline",
    "adjust": "raw"
  },
  {
    "date": "2025-06-19",
    "trade_date": "2025-06-19",
    "code": "601555",
    "open": 8.47,
    "close": 8.55,
    "high": 8.62,
    "low": 8.38,
    "volume": 74403747.0,
    "amount": null,
    "amplitude": null,
    "change_pct": null,
    "change": null,
    "turnover": null,
    "source": "sina.kline",
    "adjust": "raw"
  },
  {
    "date": "2025-06-20",
    "trade_date": "2025-06-20",
    "code": "601555",
    "open": 8.53,
    "close": 8.77,
    "high": 8.83,
    "low": 8.5,
    "volume": 100783617.0,
    "amount": null,
    "amplitude": null,
    "change_pct": null,
    "change": null,
    "turnover": null,
    "source": "sina.kline",
    "adjust": "raw"
  },
  {
    "date": "2025-06-23",
    "trade_date": "2025-06-23",
    "code": "601555",
    "open": 8.66,
    "close": 8.82,
    "high": 8.85,
    "low": 8.63,
    "volume": 72930178.0,
    "amount": null,
    "amplitude": null,
    "change_pct": null,
    "change": null,
    "turnover": null,
    "source": "sina.kline",
    "adjust": "raw"
  },
  {
    "date": "2025-06-24",
    "trade_date": "2025-06-24",
    "code": "601555",
    "open": 8.82,
    "close": 8.78,
    "high": 9.01,
    "low": 8.76,
    "volume": 116913281.0,
    "amount": null,
    "amplitude": null,
    "change_pct": null,
    "change": null,
    "turnover": null,
    "source": "sina.kline",
    "adjust": "raw"
  },
  {
    "date": "2025-06-25",
    "trade_date": "2025-06-25",
    "code": "601555",
    "open": 8.76,
    "close": 8.95,
    "high": 9.21,
    "low": 8.75,
    "volume": 215394616.0,
    "amount": null,
    "amplitude": null,
    "change_pct": null,
    "change": null,
    "turnover": null,
    "source": "sina.kline",
    "adjust": "raw"
  },
  {
    "date": "2025-06-26",
    "trade_date": "2025-06-26",
    "code": "601555",
    "open": 9.0,
    "close": 8.88,
    "high": 9.03,
    "low": 8.75,
    "volume": 106618408.0,
    "amount": null,
    "amplitude": null,
    "change_pct": null,
    "change": null,
    "turnover": null,
    "source": "sina.kline",
    "adjust": "raw"
  },
  {
    "date": "2025-06-27",
    "trade_date": "2025-06-27",
    "code": "601555",
    "open": 8.89,
    "close": 8.79,
    "high": 9.1,
    "low": 8.77,
    "volume": 112048672.0,
    "amount": null,
    "amplitude": null,
    "change_pct": null,
    "change": null,
    "turnover": null,
    "source": "sina.kline",
    "adjust": "raw"
  },
  {
    "date": "2025-06-30",
    "trade_date": "2025-06-30",
    "code": "601555",
    "open": 8.77,
    "close": 8.75,
    "high": 8.83,
    "low": 8.63,
    "volume": 71433240.0,
    "amount": null,
    "amplitude": null,
    "change_pct": null,
    "change": null,
    "turnover": null,
    "source": "sina.kline",
    "adjust": "raw"
  },
  {
    "date": "2025-07-01",
    "trade_date": "2025-07-01",
    "code": "601555",
    "open": 8.75,
    "close": 8.99,
    "high": 9.03,
    "low": 8.67,
    "volume": 81833546.0,
    "amount": null,
    "amplitude": null,
    "change_pct": null,
    "change": null,
    "turnover": null,
    "source": "sina.kline",
    "adjust": "raw"
  },
  {
    "date": "2025-07-02",
    "trade_date": "2025-07-02",
    "code": "601555",
    "open": 8.94,
    "close": 8.91,
    "high": 8.99,
    "low": 8.87,
    "volume": 49475731.0,
    "amount": null,
    "amplitude": null,
    "change_pct": null,
    "change": null,
    "turnover": null,
    "source": "sina.kline",
    "adjust": "raw"
  },
  {
    "date": "2025-07-03",
    "trade_date": "2025-07-03",
    "code": "601555",
    "open": 8.9,
    "close": 8.9,
    "high": 8.98,
    "low": 8.88,
    "volume": 40276415.0,
    "amount": null,
    "amplitude": null,
    "change_pct": null,
    "change": null,
    "turnover": null,
    "source": "sina.kline",
    "adjust": "raw"
  },
  {
    "date": "2025-07-04",
    "trade_date": "2025-07-04",
    "code": "601555",
    "open": 8.9,
    "close": 8.87,
    "high": 9.02,
    "low": 8.81,
    "volume": 62046703.0,
    "amount": null,
    "amplitude": null,
    "change_pct": null,
    "change": null,
    "turnover": null,
    "source": "sina.kline",
    "adjust": "raw"
  },
  {
    "date": "2025-07-07",
    "trade_date": "2025-07-07",
    "code": "601555",
    "open": 8.83,
    "close": 8.9,
    "high": 8.93,
    "low": 8.82,
    "volume": 32425058.0,
    "amount": null,
    "amplitude": null,
    "change_pct": null,
    "change": null,
    "turnover": null,
    "source": "sina.kline",
    "adjust": "raw"
  },
  {
    "date": "2025-07-08",
    "trade_date": "2025-07-08",
    "code": "601555",
    "open": 8.88,
    "close": 9.0,
    "high": 9.03,
    "low": 8.88,
    "volume": 70130709.0,
    "amount": null,
    "amplitude": null,
    "change_pct": null,
    "change": null,
    "turnover": null,
    "source": "sina.kline",
    "adjust": "raw"
  },
  {
    "date": "2025-07-09",
    "trade_date": "2025-07-09",
    "code": "601555",
    "open": 9.03,
    "close": 8.92,
    "high": 9.03,
    "low": 8.9,
    "volume": 40723995.0,
    "amount": null,
    "amplitude": null,
    "change_pct": null,
    "change": null,
    "turnover": null,
    "source": "sina.kline",
    "adjust": "raw"
  },
  {
    "date": "2025-07-10",
    "trade_date": "2025-07-10",
    "code": "601555",
    "open": 8.9,
    "close": 9.13,
    "high": 9.18,
    "low": 8.9,
    "volume": 113583180.0,
    "amount": null,
    "amplitude": null,
    "change_pct": null,
    "change": null,
    "turnover": null,
    "source": "sina.kline",
    "adjust": "raw"
  },
  {
    "date": "2025-07-11",
    "trade_date": "2025-07-11",
    "code": "601555",
    "open": 9.18,
    "close": 9.39,
    "high": 9.68,
    "low": 9.1,
    "volume": 232527453.0,
    "amount": null,
    "amplitude": null,
    "change_pct": null,
    "change": null,
    "turnover": null,
    "source": "sina.kline",
    "adjust": "raw"
  },
  {
    "date": "2025-07-14",
    "trade_date": "2025-07-14",
    "code": "601555",
    "open": 9.46,
    "close": 9.27,
    "high": 9.5,
    "low": 9.22,
    "volume": 94283747.0,
    "amount": null,
    "amplitude": null,
    "change_pct": null,
    "change": null,
    "turnover": null,
    "source": "sina.kline",
    "adjust": "raw"
  },
  {
    "date": "2025-07-15",
    "trade_date": "2025-07-15",
    "code": "601555",
    "open": 9.2,
    "close": 9.16,
    "high": 9.38,
    "low": 9.12,
    "volume": 103612500.0,
    "amount": null,
    "amplitude": null,
    "change_pct": null,
    "change": null,
    "turnover": null,
    "source": "sina.kline",
    "adjust": "raw"
  },
  {
    "date": "2025-07-16",
    "trade_date": "2025-07-16",
    "code": "601555",
    "open": 9.17,
    "close": 9.06,
    "high": 9.22,
    "low": 9.02,
    "volume": 60883378.0,
    "amount": null,
    "amplitude": null,
    "change_pct": null,
    "change": null,
    "turnover": null,
    "source": "sina.kline",
    "adjust": "raw"
  },
  {
    "date": "2025-07-17",
    "trade_date": "2025-07-17",
    "code": "601555",
    "open": 9.06,
    "close": 9.06,
    "high": 9.12,
    "low": 9.02,
    "volume": 62166731.0,
    "amount": null,
    "amplitude": null,
    "change_pct": null,
    "change": null,
    "turnover": null,
    "source": "sina.kline",
    "adjust": "raw"
  },
  {
    "date": "2025-07-18",
    "trade_date": "2025-07-18",
    "code": "601555",
    "open": 9.08,
    "close": 9.0,
    "high": 9.1,
    "low": 8.99,
    "volume": 71821726.0,
    "amount": null,
    "amplitude": null,
    "change_pct": null,
    "change": null,
    "turnover": null,
    "source": "sina.kline",
    "adjust": "raw"
  },
  {
    "date": "2025-07-21",
    "trade_date": "2025-07-21",
    "code": "601555",
    "open": 8.91,
    "close": 9.27,
    "high": 9.37,
    "low": 8.85,
    "volume": 154006810.0,
    "amount": null,
    "amplitude": null,
    "change_pct": null,
    "change": null,
    "turnover": null,
    "source": "sina.kline",
    "adjust": "raw"
  },
  {
    "date": "2025-07-22",
    "trade_date": "2025-07-22",
    "code": "601555",
    "open": 9.3,
    "close": 9.3,
    "high": 9.57,
    "low": 9.17,
    "volume": 111478264.0,
    "amount": null,
    "amplitude": null,
    "change_pct": null,
    "change": null,
    "turnover": null,
    "source": "sina.kline",
    "adjust": "raw"
  },
  {
    "date": "2025-07-23",
    "trade_date": "2025-07-23",
    "code": "601555",
    "open": 9.31,
    "close": 9.45,
    "high": 9.61,
    "low": 9.31,
    "volume": 146386726.0,
    "amount": null,
    "amplitude": null,
    "change_pct": null,
    "change": null,
    "turnover": null,
    "source": "sina.kline",
    "adjust": "raw"
  },
  {
    "date": "2025-07-24",
    "trade_date": "2025-07-24",
    "code": "601555",
    "open": 9.38,
    "close": 10.09,
    "high": 10.3,
    "low": 9.35,
    "volume": 205153618.0,
    "amount": null,
    "amplitude": null,
    "change_pct": null,
    "change": null,
    "turnover": null,
    "source": "sina.kline",
    "adjust": "raw"
  },
  {
    "date": "2025-07-25",
    "trade_date": "2025-07-25",
    "code": "601555",
    "open": 10.23,
    "close": 10.37,
    "high": 10.57,
    "low": 10.01,
    "volume": 235368018.0,
    "amount": null,
    "amplitude": null,
    "change_pct": null,
    "change": null,
    "turnover": null,
    "source": "sina.kline",
    "adjust": "raw"
  },
  {
    "date": "2025-07-28",
    "trade_date": "2025-07-28",
    "code": "601555",
    "open": 10.2,
    "close": 10.26,
    "high": 10.32,
    "low": 9.9,
    "volume": 209220052.0,
    "amount": null,
    "amplitude": null,
    "change_pct": null,
    "change": null,
    "turnover": null,
    "source": "sina.kline",
    "adjust": "raw"
  },
  {
    "date": "2025-07-29",
    "trade_date": "2025-07-29",
    "code": "601555",
    "open": 10.17,
    "close": 10.08,
    "high": 10.21,
    "low": 9.91,
    "volume": 124302039.0,
    "amount": null,
    "amplitude": null,
    "change_pct": null,
    "change": null,
    "turnover": null,
    "source": "sina.kline",
    "adjust": "raw"
  },
  {
    "date": "2025-07-30",
    "trade_date": "2025-07-30",
    "code": "601555",
    "open": 10.03,
    "close": 9.84,
    "high": 10.08,
    "low": 9.72,
    "volume": 116004431.0,
    "amount": null,
    "amplitude": null,
    "change_pct": null,
    "change": null,
    "turnover": null,
    "source": "sina.kline",
    "adjust": "raw"
  },
  {
    "date": "2025-07-31",
    "trade_date": "2025-07-31",
    "code": "601555",
    "open": 9.74,
    "close": 9.55,
    "high": 9.85,
    "low": 9.48,
    "volume": 112454355.0,
    "amount": null,
    "amplitude": null,
    "change_pct": null,
    "change": null,
    "turnover": null,
    "source": "sina.kline",
    "adjust": "raw"
  },
  {
    "date": "2025-08-01",
    "trade_date": "2025-08-01",
    "code": "601555",
    "open": 9.5,
    "close": 9.48,
    "high": 9.6,
    "low": 9.41,
    "volume": 83581602.0,
    "amount": null,
    "amplitude": null,
    "change_pct": null,
    "change": null,
    "turnover": null,
    "source": "sina.kline",
    "adjust": "raw"
  },
  {
    "date": "2025-08-04",
    "trade_date": "2025-08-04",
    "code": "601555",
    "open": 9.45,
    "close": 9.47,
    "high": 9.65,
    "low": 9.4,
    "volume": 84470431.0,
    "amount": null,
    "amplitude": null,
    "change_pct": null,
    "change": null,
    "turnover": null,
    "source": "sina.kline",
    "adjust": "raw"
  },
  {
    "date": "2025-08-05",
    "trade_date": "2025-08-05",
    "code": "601555",
    "open": 9.46,
    "close": 9.54,
    "high": 9.62,
    "low": 9.45,
    "volume": 84562009.0,
    "amount": null,
    "amplitude": null,
    "change_pct": null,
    "change": null,
    "turnover": null,
    "source": "sina.kline",
    "adjust": "raw"
  },
  {
    "date": "2025-08-06",
    "trade_date": "2025-08-06",
    "code": "601555",
    "open": 9.52,
    "close": 9.68,
    "high": 9.7,
    "low": 9.46,
    "volume": 95474847.0,
    "amount": null,
    "amplitude": null,
    "change_pct": null,
    "change": null,
    "turnover": null,
    "source": "sina.kline",
    "adjust": "raw"
  },
  {
    "date": "2025-08-07",
    "trade_date": "2025-08-07",
    "code": "601555",
    "open": 9.64,
    "close": 9.55,
    "high": 9.78,
    "low": 9.54,
    "volume": 115105050.0,
    "amount": null,
    "amplitude": null,
    "change_pct": null,
    "change": null,
    "turnover": null,
    "source": "sina.kline",
    "adjust": "raw"
  },
  {
    "date": "2025-08-08",
    "trade_date": "2025-08-08",
    "code": "601555",
    "open": 9.54,
    "close": 9.39,
    "high": 9.54,
    "low": 9.37,
    "volume": 92545742.0,
    "amount": null,
    "amplitude": null,
    "change_pct": null,
    "change": null,
    "turnover": null,
    "source": "sina.kline",
    "adjust": "raw"
  },
  {
    "date": "2025-08-11",
    "trade_date": "2025-08-11",
    "code": "601555",
    "open": 9.39,
    "close": 9.6,
    "high": 9.65,
    "low": 9.39,
    "volume": 105030236.0,
    "amount": null,
    "amplitude": null,
    "change_pct": null,
    "change": null,
    "turnover": null,
    "source": "sina.kline",
    "adjust": "raw"
  },
  {
    "date": "2025-08-12",
    "trade_date": "2025-08-12",
    "code": "601555",
    "open": 9.59,
    "close": 9.62,
    "high": 9.66,
    "low": 9.52,
    "volume": 66558811.0,
    "amount": null,
    "amplitude": null,
    "change_pct": null,
    "change": null,
    "turnover": null,
    "source": "sina.kline",
    "adjust": "raw"
  },
  {
    "date": "2025-08-13",
    "trade_date": "2025-08-13",
    "code": "601555",
    "open": 9.66,
    "close": 10.33,
    "high": 10.56,
    "low": 9.66,
    "volume": 312959072.0,
    "amount": null,
    "amplitude": null,
    "change_pct": null,
    "change": null,
    "turnover": null,
    "source": "sina.kline",
    "adjust": "raw"
  },
  {
    "date": "2025-08-14",
    "trade_date": "2025-08-14",
    "code": "601555",
    "open": 10.23,
    "close": 10.16,
    "high": 10.45,
    "low": 10.13,
    "volume": 195695695.0,
    "amount": null,
    "amplitude": null,
    "change_pct": null,
    "change": null,
    "turnover": null,
    "source": "sina.kline",
    "adjust": "raw"
  },
  {
    "date": "2025-08-15",
    "trade_date": "2025-08-15",
    "code": "601555",
    "open": 10.12,
    "close": 10.45,
    "high": 10.66,
    "low": 10.06,
    "volume": 216997339.0,
    "amount": null,
    "amplitude": null,
    "change_pct": null,
    "change": null,
    "turnover": null,
    "source": "sina.kline",
    "adjust": "raw"
  },
  {
    "date": "2025-08-18",
    "trade_date": "2025-08-18",
    "code": "601555",
    "open": 10.53,
    "close": 10.45,
    "high": 10.67,
    "low": 10.38,
    "volume": 215413696.0,
    "amount": null,
    "amplitude": null,
    "change_pct": null,
    "change": null,
    "turnover": null,
    "source": "sina.kline",
    "adjust": "raw"
  },
  {
    "date": "2025-08-19",
    "trade_date": "2025-08-19",
    "code": "601555",
    "open": 10.46,
    "close": 10.29,
    "high": 10.62,
    "low": 10.26,
    "volume": 122994716.0,
    "amount": null,
    "amplitude": null,
    "change_pct": null,
    "change": null,
    "turnover": null,
    "source": "sina.kline",
    "adjust": "raw"
  },
  {
    "date": "2025-08-20",
    "trade_date": "2025-08-20",
    "code": "601555",
    "open": 10.3,
    "close": 10.4,
    "high": 10.42,
    "low": 10.11,
    "volume": 96861294.0,
    "amount": null,
    "amplitude": null,
    "change_pct": null,
    "change": null,
    "turnover": null,
    "source": "sina.kline",
    "adjust": "raw"
  },
  {
    "date": "2025-08-21",
    "trade_date": "2025-08-21",
    "code": "601555",
    "open": 10.5,
    "close": 10.24,
    "high": 10.5,
    "low": 10.19,
    "volume": 93008532.0,
    "amount": null,
    "amplitude": null,
    "change_pct": null,
    "change": null,
    "turnover": null,
    "source": "sina.kline",
    "adjust": "raw"
  },
  {
    "date": "2025-08-22",
    "trade_date": "2025-08-22",
    "code": "601555",
    "open": 10.2,
    "close": 10.48,
    "high": 10.53,
    "low": 10.18,
    "volume": 135648945.0,
    "amount": null,
    "amplitude": null,
    "change_pct": null,
    "change": null,
    "turnover": null,
    "source": "sina.kline",
    "adjust": "raw"
  },
  {
    "date": "2025-08-25",
    "trade_date": "2025-08-25",
    "code": "601555",
    "open": 10.58,
    "close": 10.46,
    "high": 10.69,
    "low": 10.31,
    "volume": 209696224.0,
    "amount": null,
    "amplitude": null,
    "change_pct": null,
    "change": null,
    "turnover": null,
    "source": "sina.kline",
    "adjust": "raw"
  },
  {
    "date": "2025-08-26",
    "trade_date": "2025-08-26",
    "code": "601555",
    "open": 10.38,
    "close": 10.26,
    "high": 10.44,
    "low": 10.23,
    "volume": 135719751.0,
    "amount": null,
    "amplitude": null,
    "change_pct": null,
    "change": null,
    "turnover": null,
    "source": "sina.kline",
    "adjust": "raw"
  },
  {
    "date": "2025-08-27",
    "trade_date": "2025-08-27",
    "code": "601555",
    "open": 10.25,
    "close": 9.95,
    "high": 10.32,
    "low": 9.94,
    "volume": 158978277.0,
    "amount": null,
    "amplitude": null,
    "change_pct": null,
    "change": null,
    "turnover": null,
    "source": "sina.kline",
    "adjust": "raw"
  },
  {
    "date": "2025-08-28",
    "trade_date": "2025-08-28",
    "code": "601555",
    "open": 10.06,
    "close": 10.19,
    "high": 10.2,
    "low": 9.87,
    "volume": 124398164.0,
    "amount": null,
    "amplitude": null,
    "change_pct": null,
    "change": null,
    "turnover": null,
    "source": "sina.kline",
    "adjust": "raw"
  },
  {
    "date": "2025-08-29",
    "trade_date": "2025-08-29",
    "code": "601555",
    "open": 10.25,
    "close": 10.1,
    "high": 10.33,
    "low": 10.04,
    "volume": 141635588.0,
    "amount": null,
    "amplitude": null,
    "change_pct": null,
    "change": null,
    "turnover": null,
    "source": "sina.kline",
    "adjust": "raw"
  },
  {
    "date": "2025-09-01",
    "trade_date": "2025-09-01",
    "code": "601555",
    "open": 10.17,
    "close": 9.9,
    "high": 10.18,
    "low": 9.82,
    "volume": 156914417.0,
    "amount": null,
    "amplitude": null,
    "change_pct": null,
    "change": null,
    "turnover": null,
    "source": "sina.kline",
    "adjust": "raw"
  },
  {
    "date": "2025-09-02",
    "trade_date": "2025-09-02",
    "code": "601555",
    "open": 9.9,
    "close": 9.77,
    "high": 9.94,
    "low": 9.7,
    "volume": 103479437.0,
    "amount": null,
    "amplitude": null,
    "change_pct": null,
    "change": null,
    "turnover": null,
    "source": "sina.kline",
    "adjust": "raw"
  },
  {
    "date": "2025-09-03",
    "trade_date": "2025-09-03",
    "code": "601555",
    "open": 9.8,
    "close": 9.47,
    "high": 9.84,
    "low": 9.45,
    "volume": 111472564.0,
    "amount": null,
    "amplitude": null,
    "change_pct": null,
    "change": null,
    "turnover": null,
    "source": "sina.kline",
    "adjust": "raw"
  },
  {
    "date": "2025-09-04",
    "trade_date": "2025-09-04",
    "code": "601555",
    "open": 9.5,
    "close": 9.54,
    "high": 9.65,
    "low": 9.4,
    "volume": 109306848.0,
    "amount": null,
    "amplitude": null,
    "change_pct": null,
    "change": null,
    "turnover": null,
    "source": "sina.kline",
    "adjust": "raw"
  },
  {
    "date": "2025-09-05",
    "trade_date": "2025-09-05",
    "code": "601555",
    "open": 9.55,
    "close": 9.56,
    "high": 9.6,
    "low": 9.45,
    "volume": 94732367.0,
    "amount": null,
    "amplitude": null,
    "change_pct": null,
    "change": null,
    "turnover": null,
    "source": "sina.kline",
    "adjust": "raw"
  },
  {
    "date": "2025-09-08",
    "trade_date": "2025-09-08",
    "code": "601555",
    "open": 9.54,
    "close": 9.5,
    "high": 9.55,
    "low": 9.46,
    "volume": 82423845.0,
    "amount": null,
    "amplitude": null,
    "change_pct": null,
    "change": null,
    "turnover": null,
    "source": "sina.kline",
    "adjust": "raw"
  },
  {
    "date": "2025-09-09",
    "trade_date": "2025-09-09",
    "code": "601555",
    "open": 9.48,
    "close": 9.49,
    "high": 9.61,
    "low": 9.46,
    "volume": 99414853.0,
    "amount": null,
    "amplitude": null,
    "change_pct": null,
    "change": null,
    "turnover": null,
    "source": "sina.kline",
    "adjust": "raw"
  },
  {
    "date": "2025-09-10",
    "trade_date": "2025-09-10",
    "code": "601555",
    "open": 9.49,
    "close": 9.46,
    "high": 9.53,
    "low": 9.37,
    "volume": 81657276.0,
    "amount": null,
    "amplitude": null,
    "change_pct": null,
    "change": null,
    "turnover": null,
    "source": "sina.kline",
    "adjust": "raw"
  },
  {
    "date": "2025-09-11",
    "trade_date": "2025-09-11",
    "code": "601555",
    "open": 9.42,
    "close": 9.79,
    "high": 9.8,
    "low": 9.4,
    "volume": 125178442.0,
    "amount": null,
    "amplitude": null,
    "change_pct": null,
    "change": null,
    "turnover": null,
    "source": "sina.kline",
    "adjust": "raw"
  },
  {
    "date": "2025-09-12",
    "trade_date": "2025-09-12",
    "code": "601555",
    "open": 9.75,
    "close": 9.66,
    "high": 9.8,
    "low": 9.65,
    "volume": 82423086.0,
    "amount": null,
    "amplitude": null,
    "change_pct": null,
    "change": null,
    "turnover": null,
    "source": "sina.kline",
    "adjust": "raw"
  },
  {
    "date": "2025-09-15",
    "trade_date": "2025-09-15",
    "code": "601555",
    "open": 9.62,
    "close": 9.63,
    "high": 9.71,
    "low": 9.61,
    "volume": 60384433.0,
    "amount": null,
    "amplitude": null,
    "change_pct": null,
    "change": null,
    "turnover": null,
    "source": "sina.kline",
    "adjust": "raw"
  },
  {
    "date": "2025-09-16",
    "trade_date": "2025-09-16",
    "code": "601555",
    "open": 9.66,
    "close": 9.61,
    "high": 9.71,
    "low": 9.46,
    "volume": 87659203.0,
    "amount": null,
    "amplitude": null,
    "change_pct": null,
    "change": null,
    "turnover": null,
    "source": "sina.kline",
    "adjust": "raw"
  },
  {
    "date": "2025-09-17",
    "trade_date": "2025-09-17",
    "code": "601555",
    "open": 9.6,
    "close": 9.65,
    "high": 9.74,
    "low": 9.59,
    "volume": 69039035.0,
    "amount": null,
    "amplitude": null,
    "change_pct": null,
    "change": null,
    "turnover": null,
    "source": "sina.kline",
    "adjust": "raw"
  },
  {
    "date": "2025-09-18",
    "trade_date": "2025-09-18",
    "code": "601555",
    "open": 9.67,
    "close": 9.38,
    "high": 9.67,
    "low": 9.3,
    "volume": 129541135.0,
    "amount": null,
    "amplitude": null,
    "change_pct": null,
    "change": null,
    "turnover": null,
    "source": "sina.kline",
    "adjust": "raw"
  },
  {
    "date": "2025-09-19",
    "trade_date": "2025-09-19",
    "code": "601555",
    "open": 9.31,
    "close": 9.36,
    "high": 9.44,
    "low": 9.31,
    "volume": 49191690.0,
    "amount": null,
    "amplitude": null,
    "change_pct": null,
    "change": null,
    "turnover": null,
    "source": "sina.kline",
    "adjust": "raw"
  },
  {
    "date": "2025-09-22",
    "trade_date": "2025-09-22",
    "code": "601555",
    "open": 9.35,
    "close": 9.41,
    "high": 9.42,
    "low": 9.32,
    "volume": 44514775.0,
    "amount": null,
    "amplitude": null,
    "change_pct": null,
    "change": null,
    "turnover": null,
    "source": "sina.kline",
    "adjust": "raw"
  },
  {
    "date": "2025-09-23",
    "trade_date": "2025-09-23",
    "code": "601555",
    "open": 9.36,
    "close": 9.2,
    "high": 9.39,
    "low": 9.1,
    "volume": 73308380.0,
    "amount": null,
    "amplitude": null,
    "change_pct": null,
    "change": null,
    "turnover": null,
    "source": "sina.kline",
    "adjust": "raw"
  },
  {
    "date": "2025-09-24",
    "trade_date": "2025-09-24",
    "code": "601555",
    "open": 9.17,
    "close": 9.36,
    "high": 9.4,
    "low": 9.17,
    "volume": 53964888.0,
    "amount": null,
    "amplitude": null,
    "change_pct": null,
    "change": null,
    "turnover": null,
    "source": "sina.kline",
    "adjust": "raw"
  },
  {
    "date": "2025-09-25",
    "trade_date": "2025-09-25",
    "code": "601555",
    "open": 9.33,
    "close": 9.34,
    "high": 9.42,
    "low": 9.3,
    "volume": 46212120.0,
    "amount": null,
    "amplitude": null,
    "change_pct": null,
    "change": null,
    "turnover": null,
    "source": "sina.kline",
    "adjust": "raw"
  },
  {
    "date": "2025-09-26",
    "trade_date": "2025-09-26",
    "code": "601555",
    "open": 9.3,
    "close": 9.29,
    "high": 9.42,
    "low": 9.29,
    "volume": 37459542.0,
    "amount": null,
    "amplitude": null,
    "change_pct": null,
    "change": null,
    "turnover": null,
    "source": "sina.kline",
    "adjust": "raw"
  },
  {
    "date": "2025-09-29",
    "trade_date": "2025-09-29",
    "code": "601555",
    "open": 9.29,
    "close": 9.87,
    "high": 10.03,
    "low": 9.27,
    "volume": 192342541.0,
    "amount": null,
    "amplitude": null,
    "change_pct": null,
    "change": null,
    "turnover": null,
    "source": "sina.kline",
    "adjust": "raw"
  },
  {
    "date": "2025-09-30",
    "trade_date": "2025-09-30",
    "code": "601555",
    "open": 9.8,
    "close": 9.8,
    "high": 9.87,
    "low": 9.67,
    "volume": 96685193.0,
    "amount": null,
    "amplitude": null,
    "change_pct": null,
    "change": null,
    "turnover": null,
    "source": "sina.kline",
    "adjust": "raw"
  },
  {
    "date": "2025-10-09",
    "trade_date": "2025-10-09",
    "code": "601555",
    "open": 9.77,
    "close": 9.95,
    "high": 9.97,
    "low": 9.68,
    "volume": 106281096.0,
    "amount": null,
    "amplitude": null,
    "change_pct": null,
    "change": null,
    "turnover": null,
    "source": "sina.kline",
    "adjust": "raw"
  },
  {
    "date": "2025-10-10",
    "trade_date": "2025-10-10",
    "code": "601555",
    "open": 9.88,
    "close": 10.0,
    "high": 10.14,
    "low": 9.87,
    "volume": 101439845.0,
    "amount": null,
    "amplitude": null,
    "change_pct": null,
    "change": null,
    "turnover": null,
    "source": "sina.kline",
    "adjust": "raw"
  },
  {
    "date": "2025-10-13",
    "trade_date": "2025-10-13",
    "code": "601555",
    "open": 9.79,
    "close": 9.93,
    "high": 9.96,
    "low": 9.74,
    "volume": 85785453.0,
    "amount": null,
    "amplitude": null,
    "change_pct": null,
    "change": null,
    "turnover": null,
    "source": "sina.kline",
    "adjust": "raw"
  },
  {
    "date": "2025-10-14",
    "trade_date": "2025-10-14",
    "code": "601555",
    "open": 9.92,
    "close": 9.88,
    "high": 10.11,
    "low": 9.84,
    "volume": 76795854.0,
    "amount": null,
    "amplitude": null,
    "change_pct": null,
    "change": null,
    "turnover": null,
    "source": "sina.kline",
    "adjust": "raw"
  },
  {
    "date": "2025-10-15",
    "trade_date": "2025-10-15",
    "code": "601555",
    "open": 9.6,
    "close": 9.75,
    "high": 9.82,
    "low": 9.51,
    "volume": 106479490.0,
    "amount": null,
    "amplitude": null,
    "change_pct": null,
    "change": null,
    "turnover": null,
    "source": "sina.kline",
    "adjust": "raw"
  },
  {
    "date": "2025-10-16",
    "trade_date": "2025-10-16",
    "code": "601555",
    "open": 9.7,
    "close": 9.7,
    "high": 9.83,
    "low": 9.67,
    "volume": 65764059.0,
    "amount": null,
    "amplitude": null,
    "change_pct": null,
    "change": null,
    "turnover": null,
    "source": "sina.kline",
    "adjust": "raw"
  },
  {
    "date": "2025-10-17",
    "trade_date": "2025-10-17",
    "code": "601555",
    "open": 9.71,
    "close": 9.61,
    "high": 9.88,
    "low": 9.58,
    "volume": 86064571.0,
    "amount": null,
    "amplitude": null,
    "change_pct": null,
    "change": null,
    "turnover": null,
    "source": "sina.kline",
    "adjust": "raw"
  },
  {
    "date": "2025-10-20",
    "trade_date": "2025-10-20",
    "code": "601555",
    "open": 9.69,
    "close": 9.56,
    "high": 9.71,
    "low": 9.51,
    "volume": 57920375.0,
    "amount": null,
    "amplitude": null,
    "change_pct": null,
    "change": null,
    "turnover": null,
    "source": "sina.kline",
    "adjust": "raw"
  },
  {
    "date": "2025-10-21",
    "trade_date": "2025-10-21",
    "code": "601555",
    "open": 9.59,
    "close": 9.61,
    "high": 9.75,
    "low": 9.56,
    "volume": 63776248.0,
    "amount": null,
    "amplitude": null,
    "change_pct": null,
    "change": null,
    "turnover": null,
    "source": "sina.kline",
    "adjust": "raw"
  },
  {
    "date": "2025-10-22",
    "trade_date": "2025-10-22",
    "code": "601555",
    "open": 9.58,
    "close": 9.45,
    "high": 9.59,
    "low": 9.43,
    "volume": 52062181.0,
    "amount": null,
    "amplitude": null,
    "change_pct": null,
    "change": null,
    "turnover": null,
    "source": "sina.kline",
    "adjust": "raw"
  },
  {
    "date": "2025-10-23",
    "trade_date": "2025-10-23",
    "code": "601555",
    "open": 9.44,
    "close": 9.54,
    "high": 9.56,
    "low": 9.36,
    "volume": 40302136.0,
    "amount": null,
    "amplitude": null,
    "change_pct": null,
    "change": null,
    "turnover": null,
    "source": "sina.kline",
    "adjust": "raw"
  },
  {
    "date": "2025-10-24",
    "trade_date": "2025-10-24",
    "code": "601555",
    "open": 9.54,
    "close": 9.62,
    "high": 9.64,
    "low": 9.48,
    "volume": 53957660.0,
    "amount": null,
    "amplitude": null,
    "change_pct": null,
    "change": null,
    "turnover": null,
    "source": "sina.kline",
    "adjust": "raw"
  },
  {
    "date": "2025-10-27",
    "trade_date": "2025-10-27",
    "code": "601555",
    "open": 9.71,
    "close": 9.78,
    "high": 9.82,
    "low": 9.69,
    "volume": 87441600.0,
    "amount": null,
    "amplitude": null,
    "change_pct": null,
    "change": null,
    "turnover": null,
    "source": "sina.kline",
    "adjust": "raw"
  },
  {
    "date": "2025-10-28",
    "trade_date": "2025-10-28",
    "code": "601555",
    "open": 9.76,
    "close": 9.68,
    "high": 9.79,
    "low": 9.66,
    "volume": 49127656.0,
    "amount": null,
    "amplitude": null,
    "change_pct": null,
    "change": null,
    "turnover": null,
    "source": "sina.kline",
    "adjust": "raw"
  },
  {
    "date": "2025-10-29",
    "trade_date": "2025-10-29",
    "code": "601555",
    "open": 9.7,
    "close": 9.99,
    "high": 10.0,
    "low": 9.68,
    "volume": 124514285.0,
    "amount": null,
    "amplitude": null,
    "change_pct": null,
    "change": null,
    "turnover": null,
    "source": "sina.kline",
    "adjust": "raw"
  },
  {
    "date": "2025-10-30",
    "trade_date": "2025-10-30",
    "code": "601555",
    "open": 9.95,
    "close": 9.77,
    "high": 9.95,
    "low": 9.75,
    "volume": 80967400.0,
    "amount": null,
    "amplitude": null,
    "change_pct": null,
    "change": null,
    "turnover": null,
    "source": "sina.kline",
    "adjust": "raw"
  },
  {
    "date": "2025-10-31",
    "trade_date": "2025-10-31",
    "code": "601555",
    "open": 9.77,
    "close": 9.6,
    "high": 9.8,
    "low": 9.6,
    "volume": 74896261.0,
    "amount": null,
    "amplitude": null,
    "change_pct": null,
    "change": null,
    "turnover": null,
    "source": "sina.kline",
    "adjust": "raw"
  },
  {
    "date": "2025-11-03",
    "trade_date": "2025-11-03",
    "code": "601555",
    "open": 9.59,
    "close": 9.53,
    "high": 9.59,
    "low": 9.4,
    "volume": 61151616.0,
    "amount": null,
    "amplitude": null,
    "change_pct": null,
    "change": null,
    "turnover": null,
    "source": "sina.kline",
    "adjust": "raw"
  },
  {
    "date": "2025-11-04",
    "trade_date": "2025-11-04",
    "code": "601555",
    "open": 9.49,
    "close": 9.42,
    "high": 9.51,
    "low": 9.4,
    "volume": 46804257.0,
    "amount": null,
    "amplitude": null,
    "change_pct": null,
    "change": null,
    "turnover": null,
    "source": "sina.kline",
    "adjust": "raw"
  },
  {
    "date": "2025-11-05",
    "trade_date": "2025-11-05",
    "code": "601555",
    "open": 9.37,
    "close": 9.41,
    "high": 9.45,
    "low": 9.33,
    "volume": 30934371.0,
    "amount": null,
    "amplitude": null,
    "change_pct": null,
    "change": null,
    "turnover": null,
    "source": "sina.kline",
    "adjust": "raw"
  },
  {
    "date": "2025-11-06",
    "trade_date": "2025-11-06",
    "code": "601555",
    "open": 9.44,
    "close": 9.58,
    "high": 9.61,
    "low": 9.43,
    "volume": 55338135.0,
    "amount": null,
    "amplitude": null,
    "change_pct": null,
    "change": null,
    "turnover": null,
    "source": "sina.kline",
    "adjust": "raw"
  },
  {
    "date": "2025-11-07",
    "trade_date": "2025-11-07",
    "code": "601555",
    "open": 9.53,
    "close": 9.47,
    "high": 9.56,
    "low": 9.46,
    "volume": 36108922.0,
    "amount": null,
    "amplitude": null,
    "change_pct": null,
    "change": null,
    "turnover": null,
    "source": "sina.kline",
    "adjust": "raw"
  },
  {
    "date": "2025-11-10",
    "trade_date": "2025-11-10",
    "code": "601555",
    "open": 9.48,
    "close": 9.55,
    "high": 9.6,
    "low": 9.42,
    "volume": 39134279.0,
    "amount": null,
    "amplitude": null,
    "change_pct": null,
    "change": null,
    "turnover": null,
    "source": "sina.kline",
    "adjust": "raw"
  },
  {
    "date": "2025-11-11",
    "trade_date": "2025-11-11",
    "code": "601555",
    "open": 9.57,
    "close": 9.43,
    "high": 9.58,
    "low": 9.4,
    "volume": 44149130.0,
    "amount": null,
    "amplitude": null,
    "change_pct": null,
    "change": null,
    "turnover": null,
    "source": "sina.kline",
    "adjust": "raw"
  },
  {
    "date": "2025-11-12",
    "trade_date": "2025-11-12",
    "code": "601555",
    "open": 9.42,
    "close": 9.39,
    "high": 9.46,
    "low": 9.36,
    "volume": 33955720.0,
    "amount": null,
    "amplitude": null,
    "change_pct": null,
    "change": null,
    "turnover": null,
    "source": "sina.kline",
    "adjust": "raw"
  },
  {
    "date": "2025-11-13",
    "trade_date": "2025-11-13",
    "code": "601555",
    "open": 9.36,
    "close": 9.46,
    "high": 9.48,
    "low": 9.36,
    "volume": 32773168.0,
    "amount": null,
    "amplitude": null,
    "change_pct": null,
    "change": null,
    "turnover": null,
    "source": "sina.kline",
    "adjust": "raw"
  },
  {
    "date": "2025-11-14",
    "trade_date": "2025-11-14",
    "code": "601555",
    "open": 9.43,
    "close": 9.36,
    "high": 9.46,
    "low": 9.36,
    "volume": 30364182.0,
    "amount": null,
    "amplitude": null,
    "change_pct": null,
    "change": null,
    "turnover": null,
    "source": "sina.kline",
    "adjust": "raw"
  },
  {
    "date": "2025-11-17",
    "trade_date": "2025-11-17",
    "code": "601555",
    "open": 9.35,
    "close": 9.29,
    "high": 9.37,
    "low": 9.28,
    "volume": 34425915.0,
    "amount": null,
    "amplitude": null,
    "change_pct": null,
    "change": null,
    "turnover": null,
    "source": "sina.kline",
    "adjust": "raw"
  },
  {
    "date": "2025-11-18",
    "trade_date": "2025-11-18",
    "code": "601555",
    "open": 9.28,
    "close": 9.29,
    "high": 9.34,
    "low": 9.25,
    "volume": 28401683.0,
    "amount": null,
    "amplitude": null,
    "change_pct": null,
    "change": null,
    "turnover": null,
    "source": "sina.kline",
    "adjust": "raw"
  },
  {
    "date": "2025-11-19",
    "trade_date": "2025-11-19",
    "code": "601555",
    "open": 9.28,
    "close": 9.29,
    "high": 9.33,
    "low": 9.22,
    "volume": 27867983.0,
    "amount": null,
    "amplitude": null,
    "change_pct": null,
    "change": null,
    "turnover": null,
    "source": "sina.kline",
    "adjust": "raw"
  },
  {
    "date": "2025-11-20",
    "trade_date": "2025-11-20",
    "code": "601555",
    "open": 9.45,
    "close": 9.28,
    "high": 9.48,
    "low": 9.27,
    "volume": 52618448.0,
    "amount": null,
    "amplitude": null,
    "change_pct": null,
    "change": null,
    "turnover": null,
    "source": "sina.kline",
    "adjust": "raw"
  },
  {
    "date": "2025-11-21",
    "trade_date": "2025-11-21",
    "code": "601555",
    "open": 9.21,
    "close": 8.99,
    "high": 9.27,
    "low": 8.96,
    "volume": 76576944.0,
    "amount": null,
    "amplitude": null,
    "change_pct": null,
    "change": null,
    "turnover": null,
    "source": "sina.kline",
    "adjust": "raw"
  },
  {
    "date": "2025-11-24",
    "trade_date": "2025-11-24",
    "code": "601555",
    "open": 9.0,
    "close": 8.91,
    "high": 9.04,
    "low": 8.91,
    "volume": 34947915.0,
    "amount": null,
    "amplitude": null,
    "change_pct": null,
    "change": null,
    "turnover": null,
    "source": "sina.kline",
    "adjust": "raw"
  },
  {
    "date": "2025-11-25",
    "trade_date": "2025-11-25",
    "code": "601555",
    "open": 8.96,
    "close": 8.89,
    "high": 8.98,
    "low": 8.89,
    "volume": 31574320.0,
    "amount": null,
    "amplitude": null,
    "change_pct": null,
    "change": null,
    "turnover": null,
    "source": "sina.kline",
    "adjust": "raw"
  },
  {
    "date": "2025-11-26",
    "trade_date": "2025-11-26",
    "code": "601555",
    "open": 8.92,
    "close": 8.86,
    "high": 8.93,
    "low": 8.86,
    "volume": 22771054.0,
    "amount": null,
    "amplitude": null,
    "change_pct": null,
    "change": null,
    "turnover": null,
    "source": "sina.kline",
    "adjust": "raw"
  },
  {
    "date": "2025-11-27",
    "trade_date": "2025-11-27",
    "code": "601555",
    "open": 8.86,
    "close": 8.86,
    "high": 8.92,
    "low": 8.84,
    "volume": 20995642.0,
    "amount": null,
    "amplitude": null,
    "change_pct": null,
    "change": null,
    "turnover": null,
    "source": "sina.kline",
    "adjust": "raw"
  },
  {
    "date": "2025-11-28",
    "trade_date": "2025-11-28",
    "code": "601555",
    "open": 8.88,
    "close": 8.93,
    "high": 8.97,
    "low": 8.83,
    "volume": 28734637.0,
    "amount": null,
    "amplitude": null,
    "change_pct": null,
    "change": null,
    "turnover": null,
    "source": "sina.kline",
    "adjust": "raw"
  },
  {
    "date": "2025-12-01",
    "trade_date": "2025-12-01",
    "code": "601555",
    "open": 8.91,
    "close": 8.98,
    "high": 8.98,
    "low": 8.91,
    "volume": 24979855.0,
    "amount": null,
    "amplitude": null,
    "change_pct": null,
    "change": null,
    "turnover": null,
    "source": "sina.kline",
    "adjust": "raw"
  },
  {
    "date": "2025-12-02",
    "trade_date": "2025-12-02",
    "code": "601555",
    "open": 8.96,
    "close": 8.91,
    "high": 8.98,
    "low": 8.9,
    "volume": 16502931.0,
    "amount": null,
    "amplitude": null,
    "change_pct": null,
    "change": null,
    "turnover": null,
    "source": "sina.kline",
    "adjust": "raw"
  },
  {
    "date": "2025-12-03",
    "trade_date": "2025-12-03",
    "code": "601555",
    "open": 8.93,
    "close": 8.85,
    "high": 8.97,
    "low": 8.84,
    "volume": 24734798.0,
    "amount": null,
    "amplitude": null,
    "change_pct": null,
    "change": null,
    "turnover": null,
    "source": "sina.kline",
    "adjust": "raw"
  },
  {
    "date": "2025-12-04",
    "trade_date": "2025-12-04",
    "code": "601555",
    "open": 8.85,
    "close": 8.88,
    "high": 8.9,
    "low": 8.81,
    "volume": 17142542.0,
    "amount": null,
    "amplitude": null,
    "change_pct": null,
    "change": null,
    "turnover": null,
    "source": "sina.kline",
    "adjust": "raw"
  },
  {
    "date": "2025-12-05",
    "trade_date": "2025-12-05",
    "code": "601555",
    "open": 8.86,
    "close": 9.03,
    "high": 9.09,
    "low": 8.82,
    "volume": 58875907.0,
    "amount": null,
    "amplitude": null,
    "change_pct": null,
    "change": null,
    "turnover": null,
    "source": "sina.kline",
    "adjust": "raw"
  },
  {
    "date": "2025-12-08",
    "trade_date": "2025-12-08",
    "code": "601555",
    "open": 9.17,
    "close": 9.1,
    "high": 9.3,
    "low": 9.1,
    "volume": 79304556.0,
    "amount": null,
    "amplitude": null,
    "change_pct": null,
    "change": null,
    "turnover": null,
    "source": "sina.kline",
    "adjust": "raw"
  },
  {
    "date": "2025-12-09",
    "trade_date": "2025-12-09",
    "code": "601555",
    "open": 9.06,
    "close": 8.97,
    "high": 9.09,
    "low": 8.96,
    "volume": 31682321.0,
    "amount": null,
    "amplitude": null,
    "change_pct": null,
    "change": null,
    "turnover": null,
    "source": "sina.kline",
    "adjust": "raw"
  },
  {
    "date": "2025-12-10",
    "trade_date": "2025-12-10",
    "code": "601555",
    "open": 8.95,
    "close": 9.01,
    "high": 9.05,
    "low": 8.9,
    "volume": 31088267.0,
    "amount": null,
    "amplitude": null,
    "change_pct": null,
    "change": null,
    "turnover": null,
    "source": "sina.kline",
    "adjust": "raw"
  },
  {
    "date": "2025-12-11",
    "trade_date": "2025-12-11",
    "code": "601555",
    "open": 9.0,
    "close": 8.9,
    "high": 9.02,
    "low": 8.89,
    "volume": 22964236.0,
    "amount": null,
    "amplitude": null,
    "change_pct": null,
    "change": null,
    "turnover": null,
    "source": "sina.kline",
    "adjust": "raw"
  },
  {
    "date": "2025-12-12",
    "trade_date": "2025-12-12",
    "code": "601555",
    "open": 8.9,
    "close": 8.93,
    "high": 8.97,
    "low": 8.88,
    "volume": 31279298.0,
    "amount": null,
    "amplitude": null,
    "change_pct": null,
    "change": null,
    "turnover": null,
    "source": "sina.kline",
    "adjust": "raw"
  },
  {
    "date": "2025-12-15",
    "trade_date": "2025-12-15",
    "code": "601555",
    "open": 8.9,
    "close": 8.92,
    "high": 9.05,
    "low": 8.88,
    "volume": 41858803.0,
    "amount": null,
    "amplitude": null,
    "change_pct": null,
    "change": null,
    "turnover": null,
    "source": "sina.kline",
    "adjust": "raw"
  },
  {
    "date": "2025-12-16",
    "trade_date": "2025-12-16",
    "code": "601555",
    "open": 8.93,
    "close": 8.8,
    "high": 8.94,
    "low": 8.8,
    "volume": 39803690.0,
    "amount": null,
    "amplitude": null,
    "change_pct": null,
    "change": null,
    "turnover": null,
    "source": "sina.kline",
    "adjust": "raw"
  },
  {
    "date": "2025-12-17",
    "trade_date": "2025-12-17",
    "code": "601555",
    "open": 8.8,
    "close": 8.94,
    "high": 9.03,
    "low": 8.69,
    "volume": 59784809.0,
    "amount": null,
    "amplitude": null,
    "change_pct": null,
    "change": null,
    "turnover": null,
    "source": "sina.kline",
    "adjust": "raw"
  },
  {
    "date": "2025-12-18",
    "trade_date": "2025-12-18",
    "code": "601555",
    "open": 8.92,
    "close": 8.86,
    "high": 8.95,
    "low": 8.84,
    "volume": 36620929.0,
    "amount": null,
    "amplitude": null,
    "change_pct": null,
    "change": null,
    "turnover": null,
    "source": "sina.kline",
    "adjust": "raw"
  },
  {
    "date": "2025-12-19",
    "trade_date": "2025-12-19",
    "code": "601555",
    "open": 8.85,
    "close": 8.86,
    "high": 8.93,
    "low": 8.81,
    "volume": 35041113.0,
    "amount": null,
    "amplitude": null,
    "change_pct": null,
    "change": null,
    "turnover": null,
    "source": "sina.kline",
    "adjust": "raw"
  },
  {
    "date": "2025-12-22",
    "trade_date": "2025-12-22",
    "code": "601555",
    "open": 8.86,
    "close": 8.83,
    "high": 8.89,
    "low": 8.82,
    "volume": 29959027.0,
    "amount": null,
    "amplitude": null,
    "change_pct": null,
    "change": null,
    "turnover": null,
    "source": "sina.kline",
    "adjust": "raw"
  },
  {
    "date": "2025-12-23",
    "trade_date": "2025-12-23",
    "code": "601555",
    "open": 8.83,
    "close": 8.86,
    "high": 8.94,
    "low": 8.81,
    "volume": 34718776.0,
    "amount": null,
    "amplitude": null,
    "change_pct": null,
    "change": null,
    "turnover": null,
    "source": "sina.kline",
    "adjust": "raw"
  },
  {
    "date": "2025-12-24",
    "trade_date": "2025-12-24",
    "code": "601555",
    "open": 8.86,
    "close": 9.07,
    "high": 9.11,
    "low": 8.85,
    "volume": 64199759.0,
    "amount": null,
    "amplitude": null,
    "change_pct": null,
    "change": null,
    "turnover": null,
    "source": "sina.kline",
    "adjust": "raw"
  },
  {
    "date": "2025-12-25",
    "trade_date": "2025-12-25",
    "code": "601555",
    "open": 9.06,
    "close": 9.07,
    "high": 9.13,
    "low": 9.05,
    "volume": 39980630.0,
    "amount": null,
    "amplitude": null,
    "change_pct": null,
    "change": null,
    "turnover": null,
    "source": "sina.kline",
    "adjust": "raw"
  },
  {
    "date": "2025-12-26",
    "trade_date": "2025-12-26",
    "code": "601555",
    "open": 9.07,
    "close": 9.16,
    "high": 9.25,
    "low": 9.05,
    "volume": 52516576.0,
    "amount": null,
    "amplitude": null,
    "change_pct": null,
    "change": null,
    "turnover": null,
    "source": "sina.kline",
    "adjust": "raw"
  },
  {
    "date": "2025-12-29",
    "trade_date": "2025-12-29",
    "code": "601555",
    "open": 9.15,
    "close": 9.14,
    "high": 9.19,
    "low": 9.1,
    "volume": 27840324.0,
    "amount": null,
    "amplitude": null,
    "change_pct": null,
    "change": null,
    "turnover": null,
    "source": "sina.kline",
    "adjust": "raw"
  },
  {
    "date": "2025-12-30",
    "trade_date": "2025-12-30",
    "code": "601555",
    "open": 9.12,
    "close": 9.13,
    "high": 9.18,
    "low": 9.08,
    "volume": 28527254.0,
    "amount": null,
    "amplitude": null,
    "change_pct": null,
    "change": null,
    "turnover": null,
    "source": "sina.kline",
    "adjust": "raw"
  },
  {
    "date": "2025-12-31",
    "trade_date": "2025-12-31",
    "code": "601555",
    "open": 9.11,
    "close": 9.06,
    "high": 9.17,
    "low": 9.05,
    "volume": 32234967.0,
    "amount": null,
    "amplitude": null,
    "change_pct": null,
    "change": null,
    "turnover": null,
    "source": "sina.kline",
    "adjust": "raw"
  },
  {
    "date": "2026-01-05",
    "trade_date": "2026-01-05",
    "code": "601555",
    "open": 9.11,
    "close": 9.21,
    "high": 9.23,
    "low": 9.08,
    "volume": 47690091.0,
    "amount": null,
    "amplitude": null,
    "change_pct": null,
    "change": null,
    "turnover": null,
    "source": "sina.kline",
    "adjust": "raw"
  },
  {
    "date": "2026-01-06",
    "trade_date": "2026-01-06",
    "code": "601555",
    "open": 9.18,
    "close": 9.5,
    "high": 9.53,
    "low": 9.18,
    "volume": 112927216.0,
    "amount": null,
    "amplitude": null,
    "change_pct": null,
    "change": null,
    "turnover": null,
    "source": "sina.kline",
    "adjust": "raw"
  },
  {
    "date": "2026-01-07",
    "trade_date": "2026-01-07",
    "code": "601555",
    "open": 9.5,
    "close": 9.42,
    "high": 9.52,
    "low": 9.35,
    "volume": 62661028.0,
    "amount": null,
    "amplitude": null,
    "change_pct": null,
    "change": null,
    "turnover": null,
    "source": "sina.kline",
    "adjust": "raw"
  },
  {
    "date": "2026-01-08",
    "trade_date": "2026-01-08",
    "code": "601555",
    "open": 9.37,
    "close": 9.15,
    "high": 9.38,
    "low": 9.13,
    "volume": 78854284.0,
    "amount": null,
    "amplitude": null,
    "change_pct": null,
    "change": null,
    "turnover": null,
    "source": "sina.kline",
    "adjust": "raw"
  },
  {
    "date": "2026-01-09",
    "trade_date": "2026-01-09",
    "code": "601555",
    "open": 9.16,
    "close": 9.24,
    "high": 9.28,
    "low": 9.15,
    "volume": 46572424.0,
    "amount": null,
    "amplitude": null,
    "change_pct": null,
    "change": null,
    "turnover": null,
    "source": "sina.kline",
    "adjust": "raw"
  }
]
