[
  {
    "date": "2024-01-16",
    "open": 23.76,
    "close": 23.5,
    "high": 23.9,
    "low": 23.32,
    "volume": 40128.0,
    "amount": 94782336.0,
    "amplitude": 0.0,
    "change_pct": 0.0,
    "change": 0.0,
    "turnover": 0.0,
    "source": "tx"
  },
  {
    "date": "2024-01-17",
    "open": 23.5,
    "close": 22.9,
    "high": 23.55,
    "low": 22.9,
    "volume": 49587.0,
    "amount": 115103823.75,
    "amplitude": 2.77,
    "change_pct": -2.55,
    "change": -0.6,
    "turnover": 0.0,
    "source": "tx"
  },
  {
    "date": "2024-01-18",
    "open": 22.8,
    "close": 22.77,
    "high": 22.8,
    "low": 21.99,
    "volume": 90611.0,
    "amount": 204690249.0,
    "amplitude": 3.54,
    "change_pct": -0.57,
    "change": -0.13,
    "turnover": 0.0,
    "source": "tx"
  },
  {
    "date": "2024-01-19",
    "open": 22.77,
    "close": 22.63,
    "high": 23.3,
    "low": 22.63,
    "volume": 49953.0,
    "amount": 114055187.25,
    "amplitude": 2.94,
    "change_pct": -0.61,
    "change": -0.14,
    "turnover": 0.0,
    "source": "tx"
  },
  {
    "date": "2024-01-22",
    "open": 22.6,
    "close": 21.13,
    "high": 22.63,
    "low": 21.0,
    "volume": 106625.0,
    "amount": 232869000.0,
    "amplitude": 7.2,
    "change_pct": -6.63,
    "change": -1.5,
    "turnover": 0.0,
    "source": "tx"
  },
  {
    "date": "2024-01-23",
    "open": 21.45,
    "close": 21.66,
    "high": 21.78,
    "low": 21.0,
    "volume": 68766.0,
    "amount": 147657793.5,
    "amplitude": 3.69,
    "change_pct": 2.51,
    "change": 0.53,
    "turnover": 0.0,
    "source": "tx"
  },
  {
    "date": "2024-01-24",
    "open": 21.6,
    "close": 21.68,
    "high": 21.92,
    "low": 20.96,
    "volume": 55692.0,
    "amount": 119960568.0,
    "amplitude": 4.43,
    "change_pct": 0.09,
    "change": 0.02,
    "turnover": 0.0,
    "source": "tx"
  },
  {
    "date": "2024-01-25",
    "open": 21.67,
    "close": 22.29,
    "high": 22.33,
    "low": 21.61,
    "volume": 47953.0,
    "amount": 105376717.5,
    "amplitude": 3.32,
    "change_pct": 2.81,
    "change": 0.61,
    "turnover": 0.0,
    "source": "tx"
  },
  {
    "date": "2024-01-26",
    "open": 22.19,
    "close": 21.95,
    "high": 22.47,
    "low": 21.91,
    "volume": 47876.0,
    "amount": 105949588.0,
    "amplitude": 2.51,
    "change_pct": -1.53,
    "change": -0.34,
    "turnover": 0.0,
    "source": "tx"
  },
  {
    "date": "2024-01-29",
    "open": 22.16,
    "close": 22.17,
    "high": 22.48,
    "low": 22.12,
    "volume": 65546.0,
    "amount": 145725144.5,
    "amplitude": 1.64,
    "change_pct": 1.0,
    "change": 0.22,
    "turnover": 0.0,
    "source": "tx"
  },
  {
    "date": "2024-01-30",
    "open": 21.83,
    "close": 21.32,
    "high": 22.45,
    "low": 21.26,
    "volume": 57080.0,
    "amount": 123949220.0,
    "amplitude": 5.37,
    "change_pct": -3.83,
    "change": -0.85,
    "turnover": 0.0,
    "source": "tx"
  },
  {
    "date": "2024-01-31",
    "open": 21.25,
    "close": 20.72,
    "high": 21.64,
    "low": 20.62,
    "volume": 64947.0,
    "amount": 136762145.25,
    "amplitude": 4.78,
    "change_pct": -2.81,
    "change": -0.6,
    "turnover": 0.0,
    "source": "tx"
  },
  {
    "date": "2024-02-01",
    "open": 20.61,
    "close": 20.5,
    "high": 20.9,
    "low": 20.14,
    "volume": 61999.0,
    "amount": 127330446.25,
    "amplitude": 3.67,
    "change_pct": -1.06,
    "change": -0.22,
    "turnover": 0.0,
    "source": "tx"
  },
  {
    "date": "2024-02-02",
    "open": 20.61,
    "close": 19.99,
    "high": 20.74,
    "low": 19.36,
    "volume": 71154.0,
    "amount": 143553195.0,
    "amplitude": 6.73,
    "change_pct": -2.49,
    "change": -0.51,
    "turnover": 0.0,
    "source": "tx"
  },
  {
    "date": "2024-02-05",
    "open": 19.99,
    "close": 19.49,
    "high": 20.55,
    "low": 18.95,
    "volume": 100282.0,
    "amount": 198006809.0,
    "amplitude": 8.0,
    "change_pct": -2.5,
    "change": -0.5,
    "turnover": 0.0,
    "source": "tx"
  },
  {
    "date": "2024-02-06",
    "open": 19.25,
    "close": 21.44,
    "high": 21.44,
    "low": 19.25,
    "volume": 119174.0,
    "amount": 242459503.0,
    "amplitude": 11.24,
    "change_pct": 10.01,
    "change": 1.95,
    "turnover": 0.0,
    "source": "tx"
  },
  {
    "date": "2024-02-07",
    "open": 21.4,
    "close": 23.58,
    "high": 23.58,
    "low": 21.4,
    "volume": 175973.0,
    "amount": 395763277.0,
    "amplitude": 10.17,
    "change_pct": 9.98,
    "change": 2.14,
    "turnover": 0.0,
    "source": "tx"
  },
  {
    "date": "2024-02-08",
    "open": 23.8,
    "close": 24.0,
    "high": 25.2,
    "low": 23.6,
    "volume": 189905.0,
    "amount": 458620575.0,
    "amplitude": 6.79,
    "change_pct": 1.78,
    "change": 0.42,
    "turnover": 0.0,
    "source": "tx"
  },
  {
    "date": "2024-02-19",
    "open": 24.1,
    "close": 23.38,
    "high": 24.26,
    "low": 22.9,
    "volume": 145843.0,
    "amount": 345064538.0,
    "amplitude": 5.67,
    "change_pct": -2.58,
    "change": -0.62,
    "turnover": 0.0,
    "source": "tx"
  },
  {
    "date": "2024-02-20",
    "open": 23.3,
    "close": 23.11,
    "high": 23.31,
    "low": 22.82,
    "volume": 81557.0,
    "amount": 188682119.5,
    "amplitude": 2.1,
    "change_pct": -1.15,
    "change": -0.27,
    "turnover": 0.0,
    "source": "tx"
  },
  {
    "date": "2024-02-21",
    "open": 23.0,
    "close": 23.17,
    "high": 23.96,
    "low": 22.63,
    "volume": 105396.0,
    "amount": 244413324.0,
    "amplitude": 5.76,
    "change_pct": 0.26,
    "change": 0.06,
    "turnover": 0.0,
    "source": "tx"
  },
  {
    "date": "2024-02-22",
    "open": 23.13,
    "close": 23.18,
    "high": 23.3,
    "low": 22.96,
    "volume": 59973.0,
    "amount": 138792515.25,
    "amplitude": 1.47,
    "change_pct": 0.04,
    "change": 0.01,
    "turnover": 0.0,
    "source": "tx"
  },
  {
    "date": "2024-02-23",
    "open": 23.23,
    "close": 22.74,
    "high": 23.29,
    "low": 22.38,
    "volume": 118986.0,
    "amount": 272596926.0,
    "amplitude": 3.93,
    "change_pct": -1.9,
    "change": -0.44,
    "turnover": 0.0,
    "source": "tx"
  },
  {
    "date": "2024-02-26",
    "open": 22.62,
    "close": 22.42,
    "high": 22.66,
    "low": 22.01,
    "volume": 104043.0,
    "amount": 233342438.25,
    "amplitude": 2.86,
    "change_pct": -1.41,
    "change": -0.32,
    "turnover": 0.0,
    "source": "tx"
  },
  {
    "date": "2024-02-27",
    "open": 22.27,
    "close": 22.64,
    "high": 22.68,
    "low": 22.14,
    "volume": 93876.0,
    "amount": 210587337.0,
    "amplitude": 2.41,
    "change_pct": 0.98,
    "change": 0.22,
    "turnover": 0.0,
    "source": "tx"
  },
  {
    "date": "2024-02-28",
    "open": 22.62,
    "close": 22.14,
    "high": 23.36,
    "low": 22.12,
    "volume": 150488.0,
    "amount": 339500928.0,
    "amplitude": 5.48,
    "change_pct": -2.21,
    "change": -0.5,
    "turnover": 0.0,
    "source": "tx"
  },
  {
    "date": "2024-02-29",
    "open": 22.14,
    "close": 22.56,
    "high": 22.65,
    "low": 22.1,
    "volume": 104212.0,
    "amount": 233044085.0,
    "amplitude": 2.48,
    "change_pct": 1.9,
    "change": 0.42,
    "turnover": 0.0,
    "source": "tx"
  },
  {
    "date": "2024-03-01",
    "open": 22.53,
    "close": 22.64,
    "high": 23.0,
    "low": 22.43,
    "volume": 102075.0,
    "amount": 231199875.0,
    "amplitude": 2.53,
    "change_pct": 0.35,
    "change": 0.08,
    "turnover": 0.0,
    "source": "tx"
  },
  {
    "date": "2024-03-04",
    "open": 22.63,
    "close": 22.18,
    "high": 22.64,
    "low": 22.0,
    "volume": 109874.0,
    "amount": 245705732.5,
    "amplitude": 2.83,
    "change_pct": -2.03,
    "change": -0.46,
    "turnover": 0.0,
    "source": "tx"
  },
  {
    "date": "2024-03-05",
    "open": 22.08,
    "close": 21.91,
    "high": 22.2,
    "low": 21.77,
    "volume": 75062.0,
    "amount": 165061338.0,
    "amplitude": 1.94,
    "change_pct": -1.22,
    "change": -0.27,
    "turnover": 0.0,
    "source": "tx"
  },
  {
    "date": "2024-03-06",
    "open": 21.8,
    "close": 21.85,
    "high": 22.27,
    "low": 21.61,
    "volume": 84540.0,
    "amount": 184994655.0,
    "amplitude": 3.01,
    "change_pct": -0.27,
    "change": -0.06,
    "turnover": 0.0,
    "source": "tx"
  },
  {
    "date": "2024-03-07",
    "open": 21.81,
    "close": 21.97,
    "high": 22.6,
    "low": 21.8,
    "volume": 107866.0,
    "amount": 237790597.0,
    "amplitude": 3.66,
    "change_pct": 0.55,
    "change": 0.12,
    "turnover": 0.0,
    "source": "tx"
  },
  {
    "date": "2024-03-08",
    "open": 21.87,
    "close": 22.13,
    "high": 22.29,
    "low": 21.83,
    "volume": 57991.0,
    "amount": 127754173.0,
    "amplitude": 2.09,
    "change_pct": 0.73,
    "change": 0.16,
    "turnover": 0.0,
    "source": "tx"
  },
  {
    "date": "2024-03-11",
    "open": 22.2,
    "close": 22.61,
    "high": 22.66,
    "low": 22.15,
    "volume": 96903.0,
    "amount": 217111171.5,
    "amplitude": 2.3,
    "change_pct": 2.17,
    "change": 0.48,
    "turnover": 0.0,
    "source": "tx"
  },
  {
    "date": "2024-03-12",
    "open": 22.62,
    "close": 22.6,
    "high": 22.77,
    "low": 22.27,
    "volume": 70628.0,
    "amount": 159372082.0,
    "amplitude": 2.21,
    "change_pct": -0.04,
    "change": -0.01,
    "turnover": 0.0,
    "source": "tx"
  },
  {
    "date": "2024-03-13",
    "open": 22.7,
    "close": 22.22,
    "high": 22.75,
    "low": 22.17,
    "volume": 78047.0,
    "amount": 175293562.0,
    "amplitude": 2.57,
    "change_pct": -1.68,
    "change": -0.38,
    "turnover": 0.0,
    "source": "tx"
  },
  {
    "date": "2024-03-14",
    "open": 22.16,
    "close": 22.06,
    "high": 22.6,
    "low": 21.95,
    "volume": 71321.0,
    "amount": 158279129.25,
    "amplitude": 2.93,
    "change_pct": -0.72,
    "change": -0.16,
    "turnover": 0.0,
    "source": "tx"
  },
  {
    "date": "2024-03-15",
    "open": 21.96,
    "close": 22.48,
    "high": 22.5,
    "low": 21.82,
    "volume": 92029.0,
    "amount": 204212351.0,
    "amplitude": 3.08,
    "change_pct": 1.9,
    "change": 0.42,
    "turnover": 0.0,
    "source": "tx"
  },
  {
    "date": "2024-03-18",
    "open": 22.33,
    "close": 22.32,
    "high": 22.5,
    "low": 22.06,
    "volume": 79379.0,
    "amount": 177035014.75,
    "amplitude": 1.96,
    "change_pct": -0.71,
    "change": -0.16,
    "turnover": 0.0,
    "source": "tx"
  },
  {
    "date": "2024-03-19",
    "open": 22.3,
    "close": 22.49,
    "high": 22.8,
    "low": 22.18,
    "volume": 95603.0,
    "amount": 214557032.75,
    "amplitude": 2.78,
    "change_pct": 0.76,
    "change": 0.17,
    "turnover": 0.0,
    "source": "tx"
  },
  {
    "date": "2024-03-20",
    "open": 22.45,
    "close": 22.65,
    "high": 22.85,
    "low": 22.22,
    "volume": 75017.0,
    "amount": 169107072.25,
    "amplitude": 2.8,
    "change_pct": 0.71,
    "change": 0.16,
    "turnover": 0.0,
    "source": "tx"
  },
  {
    "date": "2024-03-21",
    "open": 22.65,
    "close": 22.47,
    "high": 22.72,
    "low": 22.36,
    "volume": 56476.0,
    "amount": 127353380.0,
    "amplitude": 1.59,
    "change_pct": -0.79,
    "change": -0.18,
    "turnover": 0.0,
    "source": "tx"
  },
  {
    "date": "2024-03-22",
    "open": 22.4,
    "close": 21.47,
    "high": 22.43,
    "low": 21.47,
    "volume": 98055.0,
    "amount": 215157183.75,
    "amplitude": 4.27,
    "change_pct": -4.45,
    "change": -1.0,
    "turnover": 0.0,
    "source": "tx"
  },
  {
    "date": "2024-03-25",
    "open": 20.83,
    "close": 20.1,
    "high": 20.9,
    "low": 19.96,
    "volume": 243373.0,
    "amount": 497636941.75,
    "amplitude": 4.38,
    "change_pct": -6.38,
    "change": -1.37,
    "turnover": 0.0,
    "source": "tx"
  },
  {
    "date": "2024-03-26",
    "open": 20.14,
    "close": 19.9,
    "high": 20.16,
    "low": 19.45,
    "volume": 168058.0,
    "amount": 334645492.5,
    "amplitude": 3.53,
    "change_pct": -1.0,
    "change": -0.2,
    "turnover": 0.0,
    "source": "tx"
  },
  {
    "date": "2024-03-27",
    "open": 19.85,
    "close": 19.08,
    "high": 19.94,
    "low": 18.95,
    "volume": 154879.0,
    "amount": 301317094.5,
    "amplitude": 4.97,
    "change_pct": -4.12,
    "change": -0.82,
    "turnover": 0.0,
    "source": "tx"
  },
  {
    "date": "2024-03-28",
    "open": 19.09,
    "close": 19.32,
    "high": 19.65,
    "low": 19.08,
    "volume": 133020.0,
    "amount": 256529070.0,
    "amplitude": 2.99,
    "change_pct": 1.26,
    "change": 0.24,
    "turnover": 0.0,
    "source": "tx"
  },
  {
    "date": "2024-03-29",
    "open": 19.31,
    "close": 19.46,
    "high": 19.53,
    "low": 19.1,
    "volume": 100162.0,
    "amount": 193813470.0,
    "amplitude": 2.23,
    "change_pct": 0.72,
    "change": 0.14,
    "turnover": 0.0,
    "source": "tx"
  },
  {
    "date": "2024-04-01",
    "open": 18.12,
    "close": 18.75,
    "high": 18.86,
    "low": 18.0,
    "volume": 572075.0,
    "amount": 1054477243.75,
    "amplitude": 4.42,
    "change_pct": -3.65,
    "change": -0.71,
    "turnover": 0.0,
    "source": "tx"
  },
  {
    "date": "2024-04-02",
    "open": 18.6,
    "close": 18.43,
    "high": 19.03,
    "low": 18.35,
    "volume": 381860.0,
    "amount": 710355065.0,
    "amplitude": 3.63,
    "change_pct": -1.71,
    "change": -0.32,
    "turnover": 0.0,
    "source": "tx"
  },
  {
    "date": "2024-04-03",
    "open": 18.45,
    "close": 20.27,
    "high": 20.27,
    "low": 18.42,
    "volume": 486393.0,
    "amount": 941292053.25,
    "amplitude": 10.04,
    "change_pct": 9.98,
    "change": 1.84,
    "turnover": 0.0,
    "source": "tx"
  },
  {
    "date": "2024-04-08",
    "open": 20.4,
    "close": 20.11,
    "high": 20.81,
    "low": 20.05,
    "volume": 589624.0,
    "amount": 1199442622.0,
    "amplitude": 3.75,
    "change_pct": -0.79,
    "change": -0.16,
    "turnover": 0.0,
    "source": "tx"
  },
  {
    "date": "2024-04-09",
    "open": 19.85,
    "close": 20.65,
    "high": 20.9,
    "low": 19.79,
    "volume": 368196.0,
    "amount": 747345831.0,
    "amplitude": 5.52,
    "change_pct": 2.69,
    "change": 0.54,
    "turnover": 0.0,
    "source": "tx"
  },
  {
    "date": "2024-04-10",
    "open": 20.65,
    "close": 20.18,
    "high": 20.88,
    "low": 20.07,
    "volume": 229044.0,
    "amount": 468280458.0,
    "amplitude": 3.92,
    "change_pct": -2.28,
    "change": -0.47,
    "turnover": 0.0,
    "source": "tx"
  }
]