[
  {
    "date": "2024-01-16",
    "open": 38.56,
    "close": 38.48,
    "high": 38.83,
    "low": 37.81,
    "volume": 27627.0,
    "amount": 106142934.0,
    "amplitude": 0.0,
    "change_pct": 0.0,
    "change": 0.0,
    "turnover": 0.0,
    "source": "tx"
  },
  {
    "date": "2024-01-17",
    "open": 38.49,
    "close": 37.43,
    "high": 38.73,
    "low": 37.42,
    "volume": 17608.0,
    "amount": 66941214.0,
    "amplitude": 3.4,
    "change_pct": -2.73,
    "change": -1.05,
    "turnover": 0.0,
    "source": "tx"
  },
  {
    "date": "2024-01-18",
    "open": 37.23,
    "close": 37.98,
    "high": 38.28,
    "low": 36.54,
    "volume": 30669.0,
    "amount": 115031751.75,
    "amplitude": 4.65,
    "change_pct": 1.47,
    "change": 0.55,
    "turnover": 0.0,
    "source": "tx"
  },
  {
    "date": "2024-01-19",
    "open": 37.98,
    "close": 37.89,
    "high": 38.68,
    "low": 37.76,
    "volume": 25083.0,
    "amount": 95509793.25,
    "amplitude": 2.42,
    "change_pct": -0.24,
    "change": -0.09,
    "turnover": 0.0,
    "source": "tx"
  },
  {
    "date": "2024-01-22",
    "open": 37.87,
    "close": 36.44,
    "high": 37.95,
    "low": 36.18,
    "volume": 31448.0,
    "amount": 116703528.0,
    "amplitude": 4.67,
    "change_pct": -3.83,
    "change": -1.45,
    "turnover": 0.0,
    "source": "tx"
  },
  {
    "date": "2024-01-23",
    "open": 36.18,
    "close": 37.29,
    "high": 37.57,
    "low": 35.82,
    "volume": 26219.0,
    "amount": 96263058.5,
    "amplitude": 4.8,
    "change_pct": 2.33,
    "change": 0.85,
    "turnover": 0.0,
    "source": "tx"
  },
  {
    "date": "2024-01-24",
    "open": 37.45,
    "close": 37.44,
    "high": 37.76,
    "low": 36.41,
    "volume": 28309.0,
    "amount": 105493488.5,
    "amplitude": 3.62,
    "change_pct": 0.4,
    "change": 0.15,
    "turnover": 0.0,
    "source": "tx"
  },
  {
    "date": "2024-01-25",
    "open": 37.56,
    "close": 38.12,
    "high": 38.24,
    "low": 36.88,
    "volume": 20393.0,
    "amount": 76881610.0,
    "amplitude": 3.63,
    "change_pct": 1.82,
    "change": 0.68,
    "turnover": 0.0,
    "source": "tx"
  },
  {
    "date": "2024-01-26",
    "open": 37.88,
    "close": 37.46,
    "high": 37.9,
    "low": 37.3,
    "volume": 23938.0,
    "amount": 90090663.0,
    "amplitude": 1.57,
    "change_pct": -1.73,
    "change": -0.66,
    "turnover": 0.0,
    "source": "tx"
  },
  {
    "date": "2024-01-29",
    "open": 37.48,
    "close": 35.78,
    "high": 37.68,
    "low": 35.72,
    "volume": 30505.0,
    "amount": 111846582.5,
    "amplitude": 5.23,
    "change_pct": -4.48,
    "change": -1.68,
    "turnover": 0.0,
    "source": "tx"
  },
  {
    "date": "2024-01-30",
    "open": 35.78,
    "close": 34.49,
    "high": 35.78,
    "low": 34.49,
    "volume": 40878.0,
    "amount": 143624853.0,
    "amplitude": 3.61,
    "change_pct": -3.61,
    "change": -1.29,
    "turnover": 0.0,
    "source": "tx"
  },
  {
    "date": "2024-01-31",
    "open": 34.28,
    "close": 32.74,
    "high": 34.67,
    "low": 32.73,
    "volume": 51302.0,
    "amount": 172400371.0,
    "amplitude": 5.62,
    "change_pct": -5.07,
    "change": -1.75,
    "turnover": 0.0,
    "source": "tx"
  },
  {
    "date": "2024-02-01",
    "open": 32.74,
    "close": 32.75,
    "high": 33.5,
    "low": 31.98,
    "volume": 38992.0,
    "amount": 127669556.0,
    "amplitude": 4.64,
    "change_pct": 0.03,
    "change": 0.01,
    "turnover": 0.0,
    "source": "tx"
  },
  {
    "date": "2024-02-02",
    "open": 32.78,
    "close": 31.59,
    "high": 33.57,
    "low": 30.48,
    "volume": 48370.0,
    "amount": 155291885.0,
    "amplitude": 9.44,
    "change_pct": -3.54,
    "change": -1.16,
    "turnover": 0.0,
    "source": "tx"
  },
  {
    "date": "2024-02-05",
    "open": 31.59,
    "close": 31.01,
    "high": 31.92,
    "low": 29.61,
    "volume": 65257.0,
    "amount": 202508785.25,
    "amplitude": 7.31,
    "change_pct": -1.84,
    "change": -0.58,
    "turnover": 0.0,
    "source": "tx"
  },
  {
    "date": "2024-02-06",
    "open": 31.01,
    "close": 33.08,
    "high": 33.22,
    "low": 30.53,
    "volume": 59710.0,
    "amount": 190833160.0,
    "amplitude": 8.67,
    "change_pct": 6.68,
    "change": 2.07,
    "turnover": 0.0,
    "source": "tx"
  },
  {
    "date": "2024-02-07",
    "open": 33.37,
    "close": 33.92,
    "high": 34.36,
    "low": 32.81,
    "volume": 49453.0,
    "amount": 166236259.5,
    "amplitude": 4.69,
    "change_pct": 2.54,
    "change": 0.84,
    "turnover": 0.0,
    "source": "tx"
  },
  {
    "date": "2024-02-08",
    "open": 33.92,
    "close": 34.58,
    "high": 34.78,
    "low": 33.11,
    "volume": 57555.0,
    "amount": 196248161.25,
    "amplitude": 4.92,
    "change_pct": 1.95,
    "change": 0.66,
    "turnover": 0.0,
    "source": "tx"
  },
  {
    "date": "2024-02-19",
    "open": 35.28,
    "close": 34.97,
    "high": 35.65,
    "low": 34.54,
    "volume": 44618.0,
    "amount": 156653798.0,
    "amplitude": 3.21,
    "change_pct": 1.13,
    "change": 0.39,
    "turnover": 0.0,
    "source": "tx"
  },
  {
    "date": "2024-02-20",
    "open": 34.61,
    "close": 35.14,
    "high": 35.27,
    "low": 34.31,
    "volume": 29432.0,
    "amount": 102519014.0,
    "amplitude": 2.75,
    "change_pct": 0.49,
    "change": 0.17,
    "turnover": 0.0,
    "source": "tx"
  },
  {
    "date": "2024-02-21",
    "open": 35.09,
    "close": 35.37,
    "high": 36.18,
    "low": 34.59,
    "volume": 38930.0,
    "amount": 137452097.5,
    "amplitude": 4.52,
    "change_pct": 0.65,
    "change": 0.23,
    "turnover": 0.0,
    "source": "tx"
  },
  {
    "date": "2024-02-22",
    "open": 35.21,
    "close": 36.12,
    "high": 36.18,
    "low": 35.21,
    "volume": 26347.0,
    "amount": 94006096.0,
    "amplitude": 2.74,
    "change_pct": 2.12,
    "change": 0.75,
    "turnover": 0.0,
    "source": "tx"
  },
  {
    "date": "2024-02-23",
    "open": 36.31,
    "close": 36.68,
    "high": 36.77,
    "low": 35.81,
    "volume": 25234.0,
    "amount": 91832834.5,
    "amplitude": 2.66,
    "change_pct": 1.55,
    "change": 0.56,
    "turnover": 0.0,
    "source": "tx"
  },
  {
    "date": "2024-02-26",
    "open": 36.57,
    "close": 36.77,
    "high": 37.24,
    "low": 36.16,
    "volume": 27848.0,
    "amount": 102160388.0,
    "amplitude": 2.94,
    "change_pct": 0.25,
    "change": 0.09,
    "turnover": 0.0,
    "source": "tx"
  },
  {
    "date": "2024-02-27",
    "open": 36.62,
    "close": 37.67,
    "high": 37.67,
    "low": 36.38,
    "volume": 35152.0,
    "amount": 130361192.0,
    "amplitude": 3.51,
    "change_pct": 2.45,
    "change": 0.9,
    "turnover": 0.0,
    "source": "tx"
  },
  {
    "date": "2024-02-28",
    "open": 37.68,
    "close": 36.06,
    "high": 38.58,
    "low": 36.06,
    "volume": 48198.0,
    "amount": 178790481.0,
    "amplitude": 6.69,
    "change_pct": -4.27,
    "change": -1.61,
    "turnover": 0.0,
    "source": "tx"
  },
  {
    "date": "2024-02-29",
    "open": 35.93,
    "close": 37.72,
    "high": 38.08,
    "low": 35.9,
    "volume": 44370.0,
    "amount": 163758577.5,
    "amplitude": 6.05,
    "change_pct": 4.6,
    "change": 1.66,
    "turnover": 0.0,
    "source": "tx"
  },
  {
    "date": "2024-03-01",
    "open": 37.87,
    "close": 38.6,
    "high": 38.88,
    "low": 37.73,
    "volume": 38387.0,
    "amount": 146907049.0,
    "amplitude": 3.05,
    "change_pct": 2.33,
    "change": 0.88,
    "turnover": 0.0,
    "source": "tx"
  },
  {
    "date": "2024-03-04",
    "open": 38.7,
    "close": 38.48,
    "high": 39.06,
    "low": 38.14,
    "volume": 27610.0,
    "amount": 106560795.0,
    "amplitude": 2.38,
    "change_pct": -0.31,
    "change": -0.12,
    "turnover": 0.0,
    "source": "tx"
  },
  {
    "date": "2024-03-05",
    "open": 38.07,
    "close": 37.98,
    "high": 38.78,
    "low": 37.71,
    "volume": 33300.0,
    "amount": 126989550.0,
    "amplitude": 2.78,
    "change_pct": -1.3,
    "change": -0.5,
    "turnover": 0.0,
    "source": "tx"
  },
  {
    "date": "2024-03-06",
    "open": 37.64,
    "close": 37.7,
    "high": 38.24,
    "low": 37.09,
    "volume": 25900.0,
    "amount": 97558825.0,
    "amplitude": 3.03,
    "change_pct": -0.74,
    "change": -0.28,
    "turnover": 0.0,
    "source": "tx"
  },
  {
    "date": "2024-03-07",
    "open": 38.05,
    "close": 36.68,
    "high": 38.08,
    "low": 36.68,
    "volume": 22905.0,
    "amount": 85601711.25,
    "amplitude": 3.71,
    "change_pct": -2.71,
    "change": -1.02,
    "turnover": 0.0,
    "source": "tx"
  },
  {
    "date": "2024-03-08",
    "open": 36.89,
    "close": 36.78,
    "high": 37.17,
    "low": 36.21,
    "volume": 16884.0,
    "amount": 62069805.0,
    "amplitude": 2.62,
    "change_pct": 0.27,
    "change": 0.1,
    "turnover": 0.0,
    "source": "tx"
  },
  {
    "date": "2024-03-11",
    "open": 36.78,
    "close": 37.56,
    "high": 37.71,
    "low": 36.42,
    "volume": 26373.0,
    "amount": 97889982.75,
    "amplitude": 3.51,
    "change_pct": 2.12,
    "change": 0.78,
    "turnover": 0.0,
    "source": "tx"
  },
  {
    "date": "2024-03-12",
    "open": 38.14,
    "close": 37.72,
    "high": 38.34,
    "low": 37.36,
    "volume": 27636.0,
    "amount": 104712804.0,
    "amplitude": 2.61,
    "change_pct": 0.43,
    "change": 0.16,
    "turnover": 0.0,
    "source": "tx"
  },
  {
    "date": "2024-03-13",
    "open": 37.98,
    "close": 37.38,
    "high": 38.11,
    "low": 37.33,
    "volume": 27688.0,
    "amount": 104383760.0,
    "amplitude": 2.07,
    "change_pct": -0.9,
    "change": -0.34,
    "turnover": 0.0,
    "source": "tx"
  },
  {
    "date": "2024-03-14",
    "open": 37.41,
    "close": 36.27,
    "high": 37.62,
    "low": 35.88,
    "volume": 43691.0,
    "amount": 160761034.5,
    "amplitude": 4.65,
    "change_pct": -2.97,
    "change": -1.11,
    "turnover": 0.0,
    "source": "tx"
  },
  {
    "date": "2024-03-15",
    "open": 36.27,
    "close": 36.08,
    "high": 36.32,
    "low": 35.47,
    "volume": 31738.0,
    "amount": 114367883.0,
    "amplitude": 2.34,
    "change_pct": -0.52,
    "change": -0.19,
    "turnover": 0.0,
    "source": "tx"
  },
  {
    "date": "2024-03-18",
    "open": 36.1,
    "close": 36.77,
    "high": 36.85,
    "low": 36.1,
    "volume": 30557.0,
    "amount": 111395543.5,
    "amplitude": 2.08,
    "change_pct": 1.91,
    "change": 0.69,
    "turnover": 0.0,
    "source": "tx"
  },
  {
    "date": "2024-03-19",
    "open": 36.68,
    "close": 36.54,
    "high": 37.16,
    "low": 36.43,
    "volume": 30316.0,
    "amount": 111267299.0,
    "amplitude": 1.99,
    "change_pct": -0.63,
    "change": -0.23,
    "turnover": 0.0,
    "source": "tx"
  },
  {
    "date": "2024-03-20",
    "open": 36.58,
    "close": 36.42,
    "high": 36.76,
    "low": 36.06,
    "volume": 25576.0,
    "amount": 93237308.0,
    "amplitude": 1.92,
    "change_pct": -0.33,
    "change": -0.12,
    "turnover": 0.0,
    "source": "tx"
  },
  {
    "date": "2024-03-21",
    "open": 36.58,
    "close": 35.76,
    "high": 36.75,
    "low": 35.71,
    "volume": 26403.0,
    "amount": 95578860.0,
    "amplitude": 2.86,
    "change_pct": -1.81,
    "change": -0.66,
    "turnover": 0.0,
    "source": "tx"
  },
  {
    "date": "2024-03-22",
    "open": 35.84,
    "close": 34.84,
    "high": 35.84,
    "low": 34.51,
    "volume": 30841.0,
    "amount": 108737655.75,
    "amplitude": 3.72,
    "change_pct": -2.57,
    "change": -0.92,
    "turnover": 0.0,
    "source": "tx"
  },
  {
    "date": "2024-03-25",
    "open": 34.81,
    "close": 33.65,
    "high": 34.83,
    "low": 33.65,
    "volume": 29772.0,
    "amount": 101924442.0,
    "amplitude": 3.39,
    "change_pct": -3.42,
    "change": -1.19,
    "turnover": 0.0,
    "source": "tx"
  },
  {
    "date": "2024-03-26",
    "open": 33.62,
    "close": 32.91,
    "high": 33.94,
    "low": 32.7,
    "volume": 29651.0,
    "amount": 98715591.75,
    "amplitude": 3.68,
    "change_pct": -2.2,
    "change": -0.74,
    "turnover": 0.0,
    "source": "tx"
  },
  {
    "date": "2024-03-27",
    "open": 33.03,
    "close": 31.81,
    "high": 33.03,
    "low": 31.81,
    "volume": 32286.0,
    "amount": 104671212.0,
    "amplitude": 3.71,
    "change_pct": -3.34,
    "change": -1.1,
    "turnover": 0.0,
    "source": "tx"
  },
  {
    "date": "2024-03-28",
    "open": 31.76,
    "close": 32.61,
    "high": 32.78,
    "low": 31.59,
    "volume": 35904.0,
    "amount": 115557024.0,
    "amplitude": 3.74,
    "change_pct": 2.51,
    "change": 0.8,
    "turnover": 0.0,
    "source": "tx"
  },
  {
    "date": "2024-03-29",
    "open": 32.63,
    "close": 33.04,
    "high": 33.14,
    "low": 31.59,
    "volume": 31455.0,
    "amount": 102543300.0,
    "amplitude": 4.75,
    "change_pct": 1.32,
    "change": 0.43,
    "turnover": 0.0,
    "source": "tx"
  },
  {
    "date": "2024-04-01",
    "open": 33.05,
    "close": 34.51,
    "high": 34.92,
    "low": 33.05,
    "volume": 41278.0,
    "amount": 139860183.5,
    "amplitude": 5.66,
    "change_pct": 4.45,
    "change": 1.47,
    "turnover": 0.0,
    "source": "tx"
  },
  {
    "date": "2024-04-02",
    "open": 34.39,
    "close": 33.77,
    "high": 34.57,
    "low": 33.51,
    "volume": 25747.0,
    "amount": 87694282.0,
    "amplitude": 3.07,
    "change_pct": -2.14,
    "change": -0.74,
    "turnover": 0.0,
    "source": "tx"
  },
  {
    "date": "2024-04-03",
    "open": 33.78,
    "close": 33.14,
    "high": 33.9,
    "low": 32.94,
    "volume": 26795.0,
    "amount": 89602480.0,
    "amplitude": 2.84,
    "change_pct": -1.87,
    "change": -0.63,
    "turnover": 0.0,
    "source": "tx"
  },
  {
    "date": "2024-04-08",
    "open": 33.07,
    "close": 32.01,
    "high": 33.07,
    "low": 31.95,
    "volume": 25259.0,
    "amount": 82154897.5,
    "amplitude": 3.38,
    "change_pct": -3.41,
    "change": -1.13,
    "turnover": 0.0,
    "source": "tx"
  },
  {
    "date": "2024-04-09",
    "open": 32.26,
    "close": 32.05,
    "high": 32.26,
    "low": 31.64,
    "volume": 26687.0,
    "amount": 85538506.75,
    "amplitude": 1.94,
    "change_pct": 0.12,
    "change": 0.04,
    "turnover": 0.0,
    "source": "tx"
  },
  {
    "date": "2024-04-10",
    "open": 32.05,
    "close": 31.0,
    "high": 32.06,
    "low": 30.78,
    "volume": 37020.0,
    "amount": 116511195.0,
    "amplitude": 3.99,
    "change_pct": -3.28,
    "change": -1.05,
    "turnover": 0.0,
    "source": "tx"
  }
]